{"verses":{"1":"قُلْ أُوحِىَ إِلَىَّ أَ<i class=tj-ghunnah>نّ</i>َهُ <i class=tj-silent>ٱ</i>سْتَمَعَ نَفَ<i class=tj-ghunnah>رٌ م</i>ِّنَ <i class=tj-silent>ٱ</i>لْجِ<i class=tj-ghunnah>نّ</i>ِ فَقَال<i class=tj-madd>ُوٓ</i><i class=tj-silent>اْ</i> إِ<i class=tj-ghunnah>نّ</i>َا سَمِعْنَا قُرْءَانًا عَجَبًا","2":"يَهْد<i class=tj-madd>ِىٓ</i> إِلَى <i class=tj-silent>ٱ</i><i class=tj-silent>ل</i>رُّشْدِ فَـَٔـامَ<i class=tj-ghunnah>نّ</i>َا بِه<i class=tj-madd>ِۦ</i>‌ۖ وَل<i class=tj-ghunnah>َن ن</i>ُّشْرِكَ بِرَبِّن<i class=tj-madd>َآ</i> أَحَدًا","3":"وَأَ<i class=tj-ghunnah>نّ</i>َهُ<i class=tj-madd>ۥ</i> تَعَ<i class=tj-madd>ـٰ</i>لَىٰ جَدُّ رَبِّنَا مَا <i class=tj-silent>ٱ</i>تَّخَذَ صَ<i class=tj-madd>ـٰ</i>حِبَ<i class=tj-ghunnah>ةً و</i>َلَا وَلَدًا","4":"وَأَ<i class=tj-ghunnah>نّ</i>َهُ<i class=tj-madd>ۥ</i> كَانَ يَقُولُ سَفِيهُنَا عَلَى <i class=tj-silent>ٱ</i>للَّهِ شَطَطًا","5":"وَأَ<i class=tj-ghunnah>نّ</i>َا ظَنَ<i class=tj-ghunnah>نّ</i><i class=tj-madd>َآ</i> أ<i class=tj-silent>َن ل</i>َّ<i class=tj-ikhfa>ن ت</i>َقُولَ <i class=tj-silent>ٱ</i>لْإِ<i class=tj-ikhfa>نس</i>ُ وَ<i class=tj-silent>ٱ</i>لْجِ<i class=tj-ghunnah>نّ</i>ُ عَلَى <i class=tj-silent>ٱ</i>للَّهِ كَذِبًا","6":"وَأَ<i class=tj-ghunnah>نّ</i>َهُ<i class=tj-madd>ۥ</i> كَانَ رِجَا<i class=tj-ghunnah>لٌ م</i>ِّنَ <i class=tj-silent>ٱ</i>لْإِ<i class=tj-ikhfa>نس</i>ِ يَعُوذُونَ بِرِجَا<i class=tj-ghunnah>لٍ م</i>ِّنَ <i class=tj-silent>ٱ</i>لْجِ<i class=tj-ghunnah>نّ</i>ِ فَزَادُوهُمْ رَهَقًا","7":"وَأَ<i class=tj-ghunnah>نّ</i>َهُمْ ظَ<i class=tj-ghunnah>نّ</i>ُو<i class=tj-silent>اْ</i> كَمَا ظَنَ<i class=tj-ikhfa>نت</i>ُمْ أ<i class=tj-silent>َن ل</i>ّ<i class=tj-ghunnah>َن ي</i>َ<i class=tj-qalqalah>بْ</i>عَثَ <i class=tj-silent>ٱ</i>للَّهُ أَحَدًا","8":"وَأَ<i class=tj-ghunnah>نّ</i>َا لَمَسْنَا <i class=tj-silent>ٱ</i><i class=tj-silent>ل</i>سَّم<i class=tj-madd>َا</i>ٓءَ فَوَجَ<i class=tj-qalqalah>دْ</i>نَ<i class=tj-madd>ـٰ</i>هَا مُلِئَتْ حَرَ<i class=tj-ikhfa>سًا ش</i>َدِي<i class=tj-ghunnah>دًا و</i>َشُهُبًا","9":"وَأَ<i class=tj-ghunnah>نّ</i>َا كُ<i class=tj-ghunnah>نّ</i>َا نَ<i class=tj-qalqalah>قْ</i>عُدُ مِنْهَا مَقَ<i class=tj-madd>ـٰ</i>عِدَ لِلسَّمْعِ‌ۖ فَم<i class=tj-ghunnah>َن ي</i>َسْتَمِعِ <i class=tj-silent>ٱ</i>لْأَنَ يَجِ<i class=tj-qalqalah>دْ</i> لَهُ<i class=tj-madd>ۥ</i> شِهَا<i class=tj-silent>بًا ر</i>َّصَدًا","10":"وَأَ<i class=tj-ghunnah>نّ</i>َا لَا نَ<i class=tj-qalqalah>دْ</i>ر<i class=tj-madd>ِىٓ</i> أَشَرٌّ أُرِيدَ بِمَ<i class=tj-ikhfa>ن ف</i>ِى <i class=tj-silent>ٱ</i>لْأَرْضِ أَمْ أَرَادَ بِهِمْ رَبُّهُمْ رَشَدًا","11":"وَأَ<i class=tj-ghunnah>نّ</i>َا مِ<i class=tj-ghunnah>نّ</i>َا <i class=tj-silent>ٱ</i><i class=tj-silent>ل</i>صَّ<i class=tj-madd>ـٰ</i>لِحُونَ وَمِ<i class=tj-ghunnah>نّ</i>َا دُونَ ذ<i class=tj-madd>َٲ</i>لِكَ‌ۖ كُ<i class=tj-ghunnah>نّ</i>َا طَر<i class=tj-madd>َا</i>ٓئِقَ قِدَدًا","12":"وَأَ<i class=tj-ghunnah>نّ</i>َا ظَنَ<i class=tj-ghunnah>نّ</i><i class=tj-madd>َآ</i> أ<i class=tj-silent>َن ل</i>ّ<i class=tj-ghunnah>َن ن</i>ُّعْجِزَ <i class=tj-silent>ٱ</i>للَّهَ فِى <i class=tj-silent>ٱ</i>لْأَرْضِ وَل<i class=tj-ghunnah>َن ن</i>ُّعْجِزَهُ<i class=tj-madd>ۥ</i> هَرَبًا","13":"وَأَ<i class=tj-ghunnah>نّ</i>َا لَ<i class=tj-ghunnah>مّ</i>َا سَمِعْنَا <i class=tj-silent>ٱ</i>لْهُدَ<i class=tj-madd>ىٰٓ</i> ءَامَ<i class=tj-ghunnah>نّ</i>َا بِه<i class=tj-madd>ِۦ</i>‌ۖ فَم<i class=tj-ghunnah>َن ي</i>ُؤْم<i class=tj-ikhfa>ِنۢ ب</i>ِرَبِّه<i class=tj-madd>ِۦ</i> فَلَا يَخَافُ بَخْ<i class=tj-ghunnah>سًا و</i>َلَا رَهَقًا","14":"وَأَ<i class=tj-ghunnah>نّ</i>َا مِ<i class=tj-ghunnah>نّ</i>َا <i class=tj-silent>ٱ</i>لْمُسْلِمُونَ وَمِ<i class=tj-ghunnah>نّ</i>َا <i class=tj-silent>ٱ</i>لْقَ<i class=tj-madd>ـٰ</i>سِطُونَ‌ۖ فَمَنْ أَسْلَمَ فَأُ<i class=tj-silent>وْ</i>لَ<i class=tj-madd>ـٰٓ</i>ئِكَ تَحَرَّوْ<i class=tj-silent>اْ</i> رَشَدًا","15":"وَأَ<i class=tj-ghunnah>مّ</i>َا <i class=tj-silent>ٱ</i>لْقَ<i class=tj-madd>ـٰ</i>سِطُونَ فَكَانُو<i class=tj-silent>اْ</i> لِجَهَ<i class=tj-ghunnah>نّ</i>َمَ حَطَبًا","16":"وَأَلَّوِ <i class=tj-silent>ٱ</i>سْتَقَ<i class=tj-madd>ـٰ</i>مُو<i class=tj-silent>اْ</i> عَلَى <i class=tj-silent>ٱ</i><i class=tj-silent>ل</i>طَّرِيقَةِ لَأَسْقَيْنَ<i class=tj-madd>ـٰ</i>ه<i class=tj-ghunnah>ُم م</i>ّ<i class=tj-madd>َا</i>ٓءً غَدَقًا","17":"لِّنَفْتِنَهُمْ فِيهِ‌ۚ وَم<i class=tj-ghunnah>َن ي</i>ُعْرِضْ عَ<i class=tj-ikhfa>ن ذ</i>ِكْرِ رَبِّه<i class=tj-madd>ِۦ</i> يَسْلُكْهُ عَذَا<i class=tj-ikhfa>بًا ص</i>َعَدًا","18":"وَأَ<i class=tj-ghunnah>نّ</i>َ <i class=tj-silent>ٱ</i>لْمَسَ<i class=tj-madd>ـٰ</i>جِدَ لِلَّهِ فَلَا تَ<i class=tj-qalqalah>دْ</i>عُو<i class=tj-silent>اْ</i> مَعَ <i class=tj-silent>ٱ</i>للَّهِ أَحَدًا","19":"وَأَ<i class=tj-ghunnah>نّ</i>َهُ<i class=tj-madd>ۥ</i> لَ<i class=tj-ghunnah>مّ</i>َا قَامَ عَ<i class=tj-qalqalah>بْ</i>دُ <i class=tj-silent>ٱ</i>للَّهِ يَ<i class=tj-qalqalah>دْ</i>عُوهُ كَادُو<i class=tj-silent>اْ</i> يَكُونُونَ عَلَيْهِ لِبَدًا","20":"قُلْ إِ<i class=tj-ghunnah>نّ</i>َم<i class=tj-madd>َآ</i> أَ<i class=tj-qalqalah>دْ</i>عُو<i class=tj-silent>اْ</i> رَبِّى وَل<i class=tj-madd>َآ</i> أُشْرِكُ بِه<i class=tj-madd>ِۦٓ</i> أَحَدًا","21":"قُلْ إِ<i class=tj-ghunnah>نّ</i>ِى ل<i class=tj-madd>َآ</i> أَمْلِكُ لَكُمْ ضَر<i class=tj-ghunnah>ًّا و</i>َلَا رَشَدًا","22":"قُلْ إِ<i class=tj-ghunnah>نّ</i>ِى ل<i class=tj-ghunnah>َن ي</i>ُجِيرَنِى مِنَ <i class=tj-silent>ٱ</i>للَّهِ أَحَ<i class=tj-ghunnah>دٌ و</i>َلَنْ أَجِدَ مِ<i class=tj-ikhfa>ن د</i>ُونِه<i class=tj-madd>ِۦ</i> مُلْتَحَدًا","23":"إِلَّا بَلَ<i class=tj-madd>ـٰ</i><i class=tj-ghunnah>غًا م</i>ِّنَ <i class=tj-silent>ٱ</i>للَّهِ وَرِسَ<i class=tj-madd>ـٰ</i>لَ<i class=tj-madd>ـٰ</i>تِه<i class=tj-madd>ِۦ</i>‌ۚ وَم<i class=tj-ghunnah>َن ي</i>َعْصِ <i class=tj-silent>ٱ</i>للَّهَ وَرَسُولَهُ<i class=tj-madd>ۥ</i> فَإِ<i class=tj-ghunnah>نّ</i>َ لَهُ<i class=tj-madd>ۥ</i> نَارَ جَهَ<i class=tj-ghunnah>نّ</i>َمَ خَ<i class=tj-madd>ـٰ</i>لِدِينَ فِيه<i class=tj-madd>َآ</i> أَبَدًا","24":"حَتَّ<i class=tj-madd>ىٰٓ</i> إِذَا رَأَوْ<i class=tj-silent>اْ</i> مَا يُوعَدُونَ فَسَيَعْلَمُونَ مَنْ أَضْعَفُ نَاصِ<i class=tj-ghunnah>رًا و</i>َأَقَلُّ عَدَدًا","25":"قُلْ إِنْ أَ<i class=tj-qalqalah>دْ</i>ر<i class=tj-madd>ِىٓ</i> أَقَرِي<i class=tj-ghunnah>بٌ م</i>َّا تُوعَدُونَ أَمْ يَ<i class=tj-qalqalah>جْ</i>عَلُ لَهُ<i class=tj-madd>ۥ</i> رَبّ<i class=tj-madd>ِىٓ</i> أَمَدًا","26":"عَ<i class=tj-madd>ـٰ</i>لِمُ <i class=tj-silent>ٱ</i>لْغَيْبِ فَلَا يُظْهِرُ عَلَىٰ غَيْبِه<i class=tj-madd>ِۦٓ</i> أَحَدًا","27":"إِلَّا مَنِ <i class=tj-silent>ٱ</i>رْتَضَىٰ م<i class=tj-silent>ِن ر</i>َّسُو<i class=tj-ikhfa>لٍ ف</i>َإِ<i class=tj-ghunnah>نّ</i>َهُ<i class=tj-madd>ۥ</i> يَسْلُكُ م<i class=tj-ikhfa>ِنۢ ب</i>َيْنِ يَدَيْهِ وَمِنْ خَلْفِه<i class=tj-madd>ِۦ</i> رَصَدًا","28":"لِّيَعْلَمَ أَ<i class=tj-ikhfa>ن ق</i>َ<i class=tj-qalqalah>دْ</i> أَ<i class=tj-qalqalah>بْ</i>لَغُو<i class=tj-silent>اْ</i> رِسَ<i class=tj-madd>ـٰ</i>لَ<i class=tj-madd>ـٰ</i>تِ رَبِّهِمْ وَأَحَاطَ بِمَا لَدَيْهِمْ وَأَحْصَىٰ كُلَّ شَىْءٍ عَدَدَۢا"}}