{"verses":{"1":"هَلْ أَتَىٰ عَلَى <i class=tj-silent>ٱ</i>لْإِ<i class=tj-ikhfa>نس</i>َ<i class=tj-madd>ـٰ</i>نِ حِي<i class=tj-ghunnah>نٌ م</i>ِّنَ <i class=tj-silent>ٱ</i><i class=tj-silent>ل</i>دَّهْرِ لَمْ يَكُ<i class=tj-ikhfa>ن ش</i>َيْـ<i class=tj-ghunnah>ـًٔا م</i>َّذْكُورًا","2":"إِ<i class=tj-ghunnah>نّ</i>َا خَلَ<i class=tj-qalqalah>قْ</i>نَا <i class=tj-silent>ٱ</i>لْإِ<i class=tj-ikhfa>نس</i>َ<i class=tj-madd>ـٰ</i>نَ م<i class=tj-ghunnah>ِن ن</i>ُّ<i class=tj-qalqalah>طْ</i>فَةٍ أَمْشَا<i class=tj-ghunnah>جٍ ن</i>َّ<i class=tj-qalqalah>بْ</i>تَلِيهِ فَجَعَلْنَ<i class=tj-madd>ـٰ</i>هُ سَمِيع<i class=tj-ikhfa>َۢا ب</i>َصِيرًا","3":"إِ<i class=tj-ghunnah>نّ</i>َا هَدَيْنَ<i class=tj-madd>ـٰ</i>هُ <i class=tj-silent>ٱ</i><i class=tj-silent>ل</i>سَّبِيلَ إِ<i class=tj-ghunnah>مّ</i>َا شَاكِ<i class=tj-ghunnah>رًا و</i>َإِ<i class=tj-ghunnah>مّ</i>َا كَفُورًا","4":"إِ<i class=tj-ghunnah>نّ</i><i class=tj-madd>َآ</i> أَعْتَ<i class=tj-qalqalah>دْ</i>نَا لِلْكَ<i class=tj-madd>ـٰ</i>فِرِينَ سَلَ<i class=tj-madd>ـٰ</i>سِلَ<i class=tj-silent>اْ</i> وَأَغْلَ<i class=tj-madd>ـٰ</i>ل<i class=tj-ghunnah>اً و</i>َسَعِيرًا","5":"إِ<i class=tj-ghunnah>نّ</i>َ <i class=tj-silent>ٱ</i>لْأَ<i class=tj-qalqalah>بْ</i>رَارَ يَشْرَبُونَ مِ<i class=tj-ikhfa>ن ك</i>َأْ<i class=tj-ikhfa>سٍ ك</i>َانَ مِزَاجُهَا كَافُورًا","6":"عَيْ<i class=tj-ghunnah>نًا ي</i>َشْرَبُ بِهَا عِبَادُ <i class=tj-silent>ٱ</i>للَّهِ يُفَجِّرُونَهَا تَفْجِيرًا","7":"يُوفُونَ بِ<i class=tj-silent>ٱ</i><i class=tj-silent>ل</i><i class=tj-ghunnah>نّ</i>َذْرِ وَيَخَافُونَ يَوْ<i class=tj-ikhfa>مًا ك</i>َانَ شَرُّهُ<i class=tj-madd>ۥ</i> مُسْتَطِيرًا","8":"وَيُ<i class=tj-qalqalah>طْ</i>عِمُونَ <i class=tj-silent>ٱ</i><i class=tj-silent>ل</i>طَّعَامَ عَلَىٰ حُبِّه<i class=tj-madd>ِۦ</i> مِسْكِي<i class=tj-ghunnah>نًا و</i>َيَتِي<i class=tj-ghunnah>مًا و</i>َأَسِيرًا","9":"إِ<i class=tj-ghunnah>نّ</i>َمَا نُ<i class=tj-qalqalah>طْ</i>عِمُكُمْ لِوَ<i class=tj-qalqalah>جْ</i>هِ <i class=tj-silent>ٱ</i>للَّهِ لَا نُرِيدُ مِ<i class=tj-ikhfa>نك</i>ُمْ جَز<i class=tj-madd>َا</i>ٓ<i class=tj-ghunnah>ءً و</i>َلَا شُكُورًا","10":"إِ<i class=tj-ghunnah>نّ</i>َا نَخَافُ م<i class=tj-silent>ِن ر</i>َّبِّنَا يَوْمًا عَبُو<i class=tj-ikhfa>سًا ق</i>َمْطَرِيرًا","11":"فَوَقَ<i class=tj-madd>ـٰ</i>هُمُ <i class=tj-silent>ٱ</i>للَّهُ شَرَّ ذ<i class=tj-madd>َٲ</i>لِكَ <i class=tj-silent>ٱ</i>لْيَوْمِ وَلَقَّ<i class=tj-madd>ـٰ</i>هُمْ نَضْرَ<i class=tj-ghunnah>ةً و</i>َسُرُورًا","12":"وَجَزَ<i class=tj-madd>ٮٰ</i>ه<i class=tj-ikhfa>ُم ب</i>ِمَا صَبَرُو<i class=tj-silent>اْ</i> جَ<i class=tj-ghunnah>نّ</i>َ<i class=tj-ghunnah>ةً و</i>َحَرِيرًا","13":"مُّتَّكِــِٔينَ فِيهَا عَلَى <i class=tj-silent>ٱ</i>لْأَر<i class=tj-madd>َا</i>ٓئِكِ‌ۖ لَا يَرَوْنَ فِيهَا شَمْ<i class=tj-ghunnah>سًا و</i>َلَا زَمْهَرِيرًا","14":"وَدَانِيَةً عَلَيْهِمْ ظِلَ<i class=tj-madd>ـٰ</i>لُهَا وَذُلِّلَتْ قُطُوفُهَا تَذْلِيلاً","15":"وَيُطَافُ عَلَيْه<i class=tj-ikhfa>ِم ب</i>ِـَٔـانِيَ<i class=tj-ghunnah>ةٍ م</i>ِّ<i class=tj-ikhfa>ن ف</i>ِضَّ<i class=tj-ghunnah>ةٍ و</i>َأَكْوَا<i class=tj-ikhfa>بٍ ك</i>َانَتْ قَوَارِيرَا۟","16":"قَوَارِيرَ<i class=tj-silent>اْ</i> مِ<i class=tj-ikhfa>ن ف</i>ِضَّ<i class=tj-ikhfa>ةٍ ق</i>َدَّرُوهَا تَ<i class=tj-qalqalah>قْ</i>دِيرًا","17":"وَيُسْقَوْنَ فِيهَا كَأْ<i class=tj-ikhfa>سًا ك</i>َانَ مِزَاجُهَا زَ<i class=tj-ikhfa>نج</i>َبِيلاً","18":"عَيْ<i class=tj-ikhfa>نًا ف</i>ِيهَا تُسَ<i class=tj-ghunnah>مّ</i>َىٰ سَلْسَبِيلاً","19":"۞ وَيَطُوفُ عَلَيْهِمْ وِلْد<i class=tj-madd>َٲ</i><i class=tj-ghunnah>نٌ م</i>ُّخَلَّدُونَ إِذَا رَأَيْتَهُمْ حَسِ<i class=tj-qalqalah>بْ</i>تَهُمْ لُؤْلُ<i class=tj-ghunnah>ؤًا م</i>َّ<i class=tj-ikhfa>نث</i>ُورًا","20":"وَإِذَا رَأَيْتَ ثَ<i class=tj-ghunnah>مّ</i>َ رَأَيْتَ نَعِي<i class=tj-ghunnah>مًا و</i>َمُلْ<i class=tj-ikhfa>كًا ك</i>َبِيرًا","21":"عَ<i class=tj-madd>ـٰ</i>لِيَهُمْ ثِيَابُ سُ<i class=tj-ikhfa>ند</i>ُسٍ خُضْ<i class=tj-ghunnah>رٌ و</i>َإِسْتَ<i class=tj-qalqalah>بْ</i>رَ<i class=tj-ghunnah>قٌ‌ۖ و</i>َحُلّ<i class=tj-madd>ُوٓ</i><i class=tj-silent>اْ</i> أَسَاوِرَ مِ<i class=tj-ikhfa>ن ف</i>ِضَّ<i class=tj-ghunnah>ةٍ و</i>َسَقَ<i class=tj-madd>ـٰ</i>هُمْ رَبُّهُمْ شَرَا<i class=tj-ikhfa>بًا ط</i>َهُورًا","22":"إِ<i class=tj-ghunnah>نّ</i>َ هَ<i class=tj-madd>ـٰ</i>ذَا كَانَ لَكُمْ جَز<i class=tj-madd>َا</i>ٓ<i class=tj-ghunnah>ءً و</i>َكَانَ سَعْيُك<i class=tj-ghunnah>ُم م</i>َّشْكُورًا","23":"إِ<i class=tj-ghunnah>نّ</i>َا نَحْنُ نَزَّلْنَا عَلَيْكَ <i class=tj-silent>ٱ</i>لْقُرْءَانَ تَ<i class=tj-ikhfa>نز</i>ِيلاً","24":"فَ<i class=tj-silent>ٱ</i>صْبِرْ لِحُكْمِ رَبِّكَ وَلَا تُطِعْ مِنْهُمْ ءَاثِمًا أَوْ كَفُورًا","25":"وَ<i class=tj-silent>ٱ</i>ذْكُرِ <i class=tj-silent>ٱ</i>سْمَ رَبِّكَ بُكْرَ<i class=tj-ghunnah>ةً و</i>َأَصِيلاً","26":"وَمِنَ <i class=tj-silent>ٱ</i>لَّيْلِ فَ<i class=tj-silent>ٱ</i>سْجُ<i class=tj-qalqalah>دْ</i> لَهُ<i class=tj-madd>ۥ</i> وَسَبِّحْهُ لَيْل<i class=tj-ikhfa>اً ط</i>َوِيلاً","27":"إِ<i class=tj-ghunnah>نّ</i>َ هَ<i class=tj-madd>ـٰٓ</i>ؤُل<i class=tj-madd>َا</i>ٓءِ يُحِبُّونَ <i class=tj-silent>ٱ</i>لْعَاجِلَةَ وَيَذَرُونَ وَر<i class=tj-madd>َا</i>ٓءَهُمْ يَوْ<i class=tj-ikhfa>مًا ث</i>َقِيلاً","28":"نَّحْنُ خَلَ<i class=tj-qalqalah>قْ</i>نَ<i class=tj-madd>ـٰ</i>هُمْ وَشَدَ<i class=tj-qalqalah>دْ</i>ن<i class=tj-madd>َآ</i> أَسْرَهُمْ‌ۖ وَإِذَا شِئْنَا بَدَّلْن<i class=tj-madd>َآ</i> أَمْثَ<i class=tj-madd>ـٰ</i>لَهُمْ تَ<i class=tj-qalqalah>بْ</i>دِيلاً","29":"إِ<i class=tj-ghunnah>نّ</i>َ هَ<i class=tj-madd>ـٰ</i>ذِه<i class=tj-madd>ِۦ</i> تَذْكِرَ<i class=tj-ikhfa>ةٌ‌ۖ ف</i>َمَ<i class=tj-ikhfa>ن ش</i><i class=tj-madd>َا</i>ٓءَ <i class=tj-silent>ٱ</i>تَّخَذَ إِلَىٰ رَبِّه<i class=tj-madd>ِۦ</i> سَبِيلاً","30":"وَمَا تَش<i class=tj-madd>َا</i>ٓءُونَ إِلّ<i class=tj-madd>َآ</i> أ<i class=tj-ghunnah>َن ي</i>َش<i class=tj-madd>َا</i>ٓءَ <i class=tj-silent>ٱ</i>للَّهُ‌ۚ إِ<i class=tj-ghunnah>نّ</i>َ <i class=tj-silent>ٱ</i>للَّهَ كَانَ عَلِيمًا حَكِيمًا","31":"يُ<i class=tj-qalqalah>دْ</i>خِلُ م<i class=tj-ghunnah>َن ي</i>َش<i class=tj-madd>َا</i>ٓءُ فِى رَحْمَتِه<i class=tj-madd>ِۦ</i>‌ۚ وَ<i class=tj-silent>ٱ</i><i class=tj-silent>ل</i>ظَّ<i class=tj-madd>ـٰ</i>لِمِينَ أَعَدَّ لَهُمْ عَذَابًا أَلِيمَۢا"}}