{"verses":{"1":"ٱلْحَمْدُ لِلَّهِ <i class=tj-silent>ٱ</i>لَّذِى لَهُ<i class=tj-madd>ۥ</i> مَا فِى <i class=tj-silent>ٱ</i><i class=tj-silent>ل</i>سَّمَ<i class=tj-madd>ـٰ</i>و<i class=tj-madd>َٲ</i>تِ وَمَا فِى <i class=tj-silent>ٱ</i>لْأَرْضِ وَلَهُ <i class=tj-silent>ٱ</i>لْحَمْدُ فِى <i class=tj-silent>ٱ</i>لْأَخِرَةِۚ وَهُوَ <i class=tj-silent>ٱ</i>لْحَكِيمُ <i class=tj-silent>ٱ</i>لْخَب<i class=tj-madd>ِي</i>رُ","2":"يَعْلَمُ مَا يَلِجُ فِى <i class=tj-silent>ٱ</i>لْأَرْضِ وَمَا يَخْرُجُ مِنْهَا وَمَا يَ<i class=tj-ikhfa>نز</i>ِلُ مِنَ <i class=tj-silent>ٱ</i><i class=tj-silent>ل</i>سَّم<i class=tj-madd>َا</i>ٓءِ وَمَا يَعْرُجُ فِيهَاۚ وَهُوَ <i class=tj-silent>ٱ</i><i class=tj-silent>ل</i>رَّحِيمُ <i class=tj-silent>ٱ</i>لْغَف<i class=tj-madd>ُو</i>رُ","3":"وَقَالَ <i class=tj-silent>ٱ</i>لَّذِينَ كَفَرُو<i class=tj-silent>اْ</i> لَا تَأْتِينَا <i class=tj-silent>ٱ</i><i class=tj-silent>ل</i>سَّاعَةُۖ قُلْ بَلَىٰ وَرَبِّى لَتَأْتِيَ<i class=tj-ghunnah>نّ</i>َكُمْ عَ<i class=tj-madd>ـٰ</i>لِمِ <i class=tj-silent>ٱ</i>لْغَيْبِۖ لَا يَعْزُبُ عَنْهُ مِثْقَالُ ذَرَّ<i class=tj-ikhfa>ةٍ ف</i>ِى <i class=tj-silent>ٱ</i><i class=tj-silent>ل</i>سَّمَ<i class=tj-madd>ـٰ</i>و<i class=tj-madd>َٲ</i>تِ وَلَا فِى <i class=tj-silent>ٱ</i>لْأَرْضِ وَل<i class=tj-madd>َآ</i> أَصْغَرُ مِ<i class=tj-ikhfa>ن ذ</i><i class=tj-madd>َٲ</i>لِكَ وَل<i class=tj-madd>َآ</i> أَكْبَرُ إِلَّا فِى كِتَ<i class=tj-madd>ـٰ</i><i class=tj-ghunnah>بٍ م</i>ُّب<i class=tj-madd>ِي</i>نٍ","4":"لِّيَ<i class=tj-qalqalah>جْ</i>زِىَ <i class=tj-silent>ٱ</i>لَّذِينَ ءَامَنُو<i class=tj-silent>اْ</i> وَعَمِلُو<i class=tj-silent>اْ</i> <i class=tj-silent>ٱ</i><i class=tj-silent>ل</i>صَّ<i class=tj-madd>ـٰ</i>لِحَ<i class=tj-madd>ـٰ</i>تِۚ أُ<i class=tj-silent>وْ</i>لَ<i class=tj-madd>ـٰٓ</i>ئِكَ لَه<i class=tj-ghunnah>ُم م</i>َّغْفِرَ<i class=tj-ghunnah>ةٌ و</i>َرِزْ<i class=tj-ikhfa>قٌ ك</i>َر<i class=tj-madd>ِي</i>مٌ","5":"وَ<i class=tj-silent>ٱ</i>لَّذِينَ سَعَوْ ف<i class=tj-madd>ِىٓ</i> ءَايَ<i class=tj-madd>ـٰ</i>تِنَا مُعَ<i class=tj-madd>ـٰ</i>جِزِينَ أُ<i class=tj-silent>وْ</i>لَ<i class=tj-madd>ـٰٓ</i>ئِكَ لَهُمْ عَذَا<i class=tj-ghunnah>بٌ م</i>ّ<i class=tj-silent>ِن ر</i>ِّ<i class=tj-qalqalah>جْ</i>زٍ أَل<i class=tj-madd>ِي</i>مٌ","6":"وَيَرَى <i class=tj-silent>ٱ</i>لَّذِينَ أُوتُو<i class=tj-silent>اْ</i> <i class=tj-silent>ٱ</i>لْعِلْمَ <i class=tj-silent>ٱ</i>لَّذ<i class=tj-madd>ِىٓ</i> أُ<i class=tj-ikhfa>نز</i>ِلَ إِلَيْكَ م<i class=tj-silent>ِن ر</i>َّبِّكَ هُوَ <i class=tj-silent>ٱ</i>لْحَقَّ وَيَهْد<i class=tj-madd>ِىٓ</i> إِلَىٰ صِر<i class=tj-madd>َٲ</i>طِ <i class=tj-silent>ٱ</i>لْعَزِيزِ <i class=tj-silent>ٱ</i>لْحَم<i class=tj-madd>ِي</i><i class=tj-qalqalah>د</i>ِ","7":"وَقَالَ <i class=tj-silent>ٱ</i>لَّذِينَ كَفَرُو<i class=tj-silent>اْ</i> هَلْ نَدُلُّكُمْ عَلَىٰ رَجُ<i class=tj-ghunnah>لٍ ي</i>ُنَبِّئُكُمْ إِذَا مُزِّ<i class=tj-qalqalah>قْ</i>تُمْ كُلَّ مُمَزَّقٍ إِ<i class=tj-ghunnah>نّ</i>َكُمْ لَفِى خَلْ<i class=tj-ikhfa>قٍ ج</i>َد<i class=tj-madd>ِي</i><i class=tj-qalqalah>د</i>ٍ","8":"أَفْتَرَىٰ عَلَى <i class=tj-silent>ٱ</i>للَّهِ كَذِبًا أ<i class=tj-ikhfa>َم ب</i>ِه<i class=tj-madd>ِۦ</i> جِ<i class=tj-ghunnah>نّ</i>َۗ<i class=tj-ikhfa>ةُۢ ب</i>َلِ <i class=tj-silent>ٱ</i>لَّذِينَ لَا يُؤْمِنُونَ بِ<i class=tj-silent>ٱ</i>لْأَخِرَةِ فِى <i class=tj-silent>ٱ</i>لْعَذَابِ وَ<i class=tj-silent>ٱ</i><i class=tj-silent>ل</i>ضَّلَ<i class=tj-madd>ـٰ</i>لِ <i class=tj-silent>ٱ</i>لْبَع<i class=tj-madd>ِي</i><i class=tj-qalqalah>د</i>ِ","9":"أَفَلَمْ يَرَوْ<i class=tj-silent>اْ</i> إِلَىٰ مَا بَيْنَ أَيْدِيهِمْ وَمَا خَلْفَه<i class=tj-ghunnah>ُم م</i>ِّنَ <i class=tj-silent>ٱ</i><i class=tj-silent>ل</i>سَّم<i class=tj-madd>َا</i>ٓءِ وَ<i class=tj-silent>ٱ</i>لْأَرْضِۚ إ<i class=tj-ghunnah>ِن ن</i>َّشَأْ نَخْسِفْ بِهِمُ <i class=tj-silent>ٱ</i>لْأَرْضَ أَوْ نُسْقِ<i class=tj-qalqalah>طْ</i> عَلَيْهِمْ كِسَ<i class=tj-ghunnah>فًا م</i>ِّنَ <i class=tj-silent>ٱ</i><i class=tj-silent>ل</i>سَّم<i class=tj-madd>َا</i>ٓءِۚ إِ<i class=tj-ghunnah>نّ</i>َ فِى ذ<i class=tj-madd>َٲ</i>لِكَ لَأَيَ<i class=tj-silent>ةً ل</i>ِّكُلِّ عَ<i class=tj-qalqalah>بْ</i><i class=tj-ghunnah>دٍ م</i>ُّن<i class=tj-madd>ِي</i><i class=tj-qalqalah>ب</i>ٍ","10":"۞ وَلَقَ<i class=tj-qalqalah>دْ</i> ءَاتَيْنَا دَاوُ<i class=tj-madd>ۥ</i>دَ مِ<i class=tj-ghunnah>نّ</i>َا فَضْل<i class=tj-ghunnah>اًۖ ي</i>َ<i class=tj-madd>ـٰ</i>جِبَالُ أَوِّبِى مَعَهُ<i class=tj-madd>ۥ</i> وَ<i class=tj-silent>ٱ</i><i class=tj-silent>ل</i>طَّيْرَۖ وَأَلَ<i class=tj-ghunnah>نّ</i>َا لَهُ <i class=tj-silent>ٱ</i>لْحَد<i class=tj-madd>ِي</i><i class=tj-qalqalah>د</i>َ","11":"أَنِ <i class=tj-silent>ٱ</i>عْمَلْ سَ<i class=tj-madd>ـٰ</i>بِغَ<i class=tj-madd>ـٰ</i><i class=tj-ghunnah>تٍ و</i>َقَدِّرْ فِى <i class=tj-silent>ٱ</i><i class=tj-silent>ل</i>سَّرْدِۖ وَ<i class=tj-silent>ٱ</i>عْمَلُو<i class=tj-silent>اْ</i> صَ<i class=tj-madd>ـٰ</i>لِحًاۖ إِ<i class=tj-ghunnah>نّ</i>ِى بِمَا تَعْمَلُونَ بَص<i class=tj-madd>ِي</i>رٌ","12":"وَلِسُلَيْمَ<i class=tj-madd>ـٰ</i>نَ <i class=tj-silent>ٱ</i><i class=tj-silent>ل</i>رِّيحَ غُدُوُّهَا شَهْ<i class=tj-ghunnah>رٌ و</i>َرَوَاحُهَا شَهْ<i class=tj-ghunnah>رٌۖ و</i>َأَسَلْنَا لَهُ<i class=tj-madd>ۥ</i> عَيْنَ <i class=tj-silent>ٱ</i>لْقِ<i class=tj-qalqalah>طْ</i>رِۖ وَمِنَ <i class=tj-silent>ٱ</i>لْجِ<i class=tj-ghunnah>نّ</i>ِ م<i class=tj-ghunnah>َن ي</i>َعْمَلُ بَيْنَ يَدَيْهِ بِإِذْنِ رَبِّهِ<i class=tj-madd>ۖۦ</i> وَم<i class=tj-ghunnah>َن ي</i>َزِغْ مِنْهُمْ عَنْ أَمْرِنَا نُذِ<i class=tj-qalqalah>قْ</i>هُ مِنْ عَذَابِ <i class=tj-silent>ٱ</i><i class=tj-silent>ل</i>سَّع<i class=tj-madd>ِي</i>رِ","13":"يَعْمَلُونَ لَهُ<i class=tj-madd>ۥ</i> مَا يَش<i class=tj-madd>َا</i>ٓءُ م<i class=tj-ghunnah>ِن م</i>َّحَ<i class=tj-madd>ـٰ</i>رِيبَ وَتَمَ<i class=tj-madd>ـٰ</i>ثِيلَ وَجِفَا<i class=tj-ikhfa>نٍ ك</i>َ<i class=tj-silent>ٱ</i>لْجَوَابِ وَقُدُو<i class=tj-silent>رٍ ر</i>َّاسِيَ<i class=tj-madd>ـٰ</i>تٍۚ <i class=tj-silent>ٱ</i>عْمَل<i class=tj-madd>ُوٓ</i><i class=tj-silent>اْ</i> ءَالَ دَاوُ<i class=tj-madd>ۥ</i>دَ شُكْ<i class=tj-ghunnah>رًاۚ و</i>َقَلِي<i class=tj-ghunnah>لٌ م</i>ِّنْ عِبَادِىَ <i class=tj-silent>ٱ</i><i class=tj-silent>ل</i>شَّك<i class=tj-madd>ُو</i>رُ","14":"فَلَ<i class=tj-ghunnah>مّ</i>َا قَضَيْنَا عَلَيْهِ <i class=tj-silent>ٱ</i>لْمَوْتَ مَا دَلَّهُمْ عَلَىٰ مَوْتِه<i class=tj-madd>ِۦٓ</i> إِلَّا د<i class=tj-madd>َا</i>ٓبَّةُ <i class=tj-silent>ٱ</i>لْأَرْضِ تَأْكُلُ مِ<i class=tj-ikhfa>نس</i>َأَتَهُۖ<i class=tj-madd>ۥ</i> فَلَ<i class=tj-ghunnah>مّ</i>َا خَرَّ تَبَيَّنَتِ <i class=tj-silent>ٱ</i>لْجِ<i class=tj-ghunnah>نّ</i>ُ أ<i class=tj-silent>َن ل</i>َّوْ كَانُو<i class=tj-silent>اْ</i> يَعْلَمُونَ <i class=tj-silent>ٱ</i>لْغَيْبَ مَا لَبِثُو<i class=tj-silent>اْ</i> فِى <i class=tj-silent>ٱ</i>لْعَذَابِ <i class=tj-silent>ٱ</i>لْمُه<i class=tj-madd>ِي</i>نِ","15":"لَقَ<i class=tj-qalqalah>دْ</i> كَانَ لِسَبَ<i class=tj-ikhfa>إٍ ف</i>ِى مَسْكَنِهِمْ ءَايَ<i class=tj-ikhfa>ةٌۖ ج</i>َ<i class=tj-ghunnah>نّ</i>َتَانِ ع<i class=tj-ghunnah>َن ي</i>َمِي<i class=tj-ghunnah>نٍ و</i>َشِمَا<i class=tj-ikhfa>لٍۖ ك</i>ُلُو<i class=tj-silent>اْ</i> م<i class=tj-silent>ِن ر</i>ِّزْقِ رَبِّكُمْ وَ<i class=tj-silent>ٱ</i>شْكُرُو<i class=tj-silent>اْ</i> لَهُۚ<i class=tj-madd>ۥ</i> بَلْدَ<i class=tj-ikhfa>ةٌ ط</i>َيِّبَ<i class=tj-ghunnah>ةٌ و</i>َرَبٌّ غَف<i class=tj-madd>ُو</i>رٌ","16":"فَأَعْرَضُو<i class=tj-silent>اْ</i> فَأَرْسَلْنَا عَلَيْهِمْ سَيْلَ <i class=tj-silent>ٱ</i>لْعَرِمِ وَبَدَّلْنَ<i class=tj-madd>ـٰ</i>ه<i class=tj-ikhfa>ُم ب</i>ِجَ<i class=tj-ghunnah>نّ</i>َتَيْهِمْ جَ<i class=tj-ghunnah>نّ</i>َتَيْنِ ذَوَات<i class=tj-madd>َىْ</i> أُكُلٍ خَمْ<i class=tj-ghunnah>طٍ و</i>َأَثْ<i class=tj-ghunnah>لٍ و</i>َش<i class=tj-ghunnah>َىْءٍ م</i>ِّ<i class=tj-ikhfa>ن س</i>ِ<i class=tj-qalqalah>دْ</i><i class=tj-ikhfa>رٍ ق</i>َل<i class=tj-madd>ِي</i>لٍ","17":"ذ<i class=tj-madd>َٲ</i>لِكَ جَزَيْنَ<i class=tj-madd>ـٰ</i>ه<i class=tj-ikhfa>ُم ب</i>ِمَا كَفَرُو<i class=tj-silent>اْۖ</i> وَهَلْ نُجَ<i class=tj-madd>ـٰ</i>ز<i class=tj-madd>ِىٓ</i> إِلَّا <i class=tj-silent>ٱ</i>لْكَف<i class=tj-madd>ُو</i>رَ","18":"وَجَعَلْنَا بَيْنَهُمْ وَبَيْنَ <i class=tj-silent>ٱ</i>لْقُرَى <i class=tj-silent>ٱ</i>لَّتِى بَ<i class=tj-madd>ـٰ</i>رَكْنَا فِيهَا قُ<i class=tj-ikhfa>رًى ظ</i>َ<i class=tj-madd>ـٰ</i>هِرَ<i class=tj-ghunnah>ةً و</i>َقَدَّرْنَا فِيهَا <i class=tj-silent>ٱ</i><i class=tj-silent>ل</i>سَّيْرَۖ سِيرُو<i class=tj-silent>اْ</i> فِيهَا لَيَالِىَ وَأَيَّامًا ءَامِن<i class=tj-madd>ِي</i>نَ","19":"فَقَالُو<i class=tj-silent>اْ</i> رَبَّنَا بَ<i class=tj-madd>ـٰ</i>عِ<i class=tj-qalqalah>دْ</i> بَيْنَ أَسْفَارِنَا وَظَلَم<i class=tj-madd>ُوٓ</i><i class=tj-silent>اْ</i> أَ<i class=tj-ikhfa>نف</i>ُسَهُمْ فَجَعَلْنَ<i class=tj-madd>ـٰ</i>هُمْ أَحَادِيثَ وَمَزَّ<i class=tj-qalqalah>قْ</i>نَ<i class=tj-madd>ـٰ</i>هُمْ كُلَّ مُمَزَّقٍۚ إِ<i class=tj-ghunnah>نّ</i>َ فِى ذ<i class=tj-madd>َٲ</i>لِكَ لَأَيَ<i class=tj-madd>ـٰ</i><i class=tj-silent>تٍ ل</i>ِّكُلِّ صَبَّا<i class=tj-ikhfa>رٍ ش</i>َك<i class=tj-madd>ُو</i>رٍ","20":"وَلَقَ<i class=tj-qalqalah>دْ</i> صَدَّقَ عَلَيْهِمْ إِ<i class=tj-qalqalah>بْ</i>لِيسُ ظَ<i class=tj-ghunnah>نّ</i>َهُ<i class=tj-madd>ۥ</i> فَ<i class=tj-silent>ٱ</i>تَّبَعُوهُ إِلَّا فَرِي<i class=tj-ghunnah>قًا م</i>ِّنَ <i class=tj-silent>ٱ</i>لْمُؤْمِن<i class=tj-madd>ِي</i>نَ","21":"وَمَا كَانَ لَهُ<i class=tj-madd>ۥ</i> عَلَيْه<i class=tj-ghunnah>ِم م</i>ِّ<i class=tj-ikhfa>ن س</i>ُلْطَ<i class=tj-madd>ـٰ</i>نٍ إِلَّا لِنَعْلَمَ م<i class=tj-ghunnah>َن ي</i>ُؤْمِنُ بِ<i class=tj-silent>ٱ</i>لْأَخِرَةِ مِ<i class=tj-ghunnah>مّ</i>َنْ هُوَ مِنْهَا فِى شَ<i class=tj-ghunnah>كٍّۗ و</i>َرَبُّكَ عَلَىٰ كُلِّ شَىْءٍ حَف<i class=tj-madd>ِي</i>ظٌ","22":"قُلِ <i class=tj-silent>ٱ</i><i class=tj-qalqalah>دْ</i>عُو<i class=tj-silent>اْ</i> <i class=tj-silent>ٱ</i>لَّذِينَ زَعَمْت<i class=tj-ghunnah>ُم م</i>ِّ<i class=tj-ikhfa>ن د</i>ُونِ <i class=tj-silent>ٱ</i>للَّهِۖ لَا يَمْلِكُونَ مِثْقَالَ ذَرَّ<i class=tj-ikhfa>ةٍ ف</i>ِى <i class=tj-silent>ٱ</i><i class=tj-silent>ل</i>سَّمَ<i class=tj-madd>ـٰ</i>و<i class=tj-madd>َٲ</i>تِ وَلَا فِى <i class=tj-silent>ٱ</i>لْأَرْضِ وَمَا لَهُمْ فِيهِمَا مِ<i class=tj-ikhfa>ن ش</i>ِرْ<i class=tj-ghunnah>كٍ و</i>َمَا لَهُ<i class=tj-madd>ۥ</i> مِنْه<i class=tj-ghunnah>ُم م</i>ِّ<i class=tj-ikhfa>ن ظ</i>َه<i class=tj-madd>ِي</i>رٍ","23":"وَلَا تَ<i class=tj-ikhfa>نف</i>َعُ <i class=tj-silent>ٱ</i><i class=tj-silent>ل</i>شَّفَ<i class=tj-madd>ـٰ</i>عَةُ عِ<i class=tj-ikhfa>ند</i>َهُ<i class=tj-madd>ۥٓ</i> إِلَّا لِمَنْ أَذِنَ لَهُۚ<i class=tj-madd>ۥ</i> حَتَّ<i class=tj-madd>ىٰٓ</i> إِذَا فُزِّعَ عَ<i class=tj-ikhfa>ن ق</i>ُلُوبِهِمْ قَالُو<i class=tj-silent>اْ</i> مَاذَا قَالَ رَبُّكُمْۖ قَالُو<i class=tj-silent>اْ</i> <i class=tj-silent>ٱ</i>لْحَقَّۖ وَهُوَ <i class=tj-silent>ٱ</i>لْعَلِىُّ <i class=tj-silent>ٱ</i>لْكَب<i class=tj-madd>ِي</i>رُ","24":"۞ قُلْ م<i class=tj-ghunnah>َن ي</i>َرْزُقُك<i class=tj-ghunnah>ُم م</i>ِّنَ <i class=tj-silent>ٱ</i><i class=tj-silent>ل</i>سَّمَ<i class=tj-madd>ـٰ</i>و<i class=tj-madd>َٲ</i>تِ وَ<i class=tj-silent>ٱ</i>لْأَرْضِۖ قُلِ <i class=tj-silent>ٱ</i>للَّهُۖ وَإِ<i class=tj-ghunnah>نّ</i><i class=tj-madd>َآ</i> أَوْ إِيَّاكُمْ لَعَلَىٰ هُدًى أَوْ فِى ضَلَ<i class=tj-madd>ـٰ</i><i class=tj-ghunnah>لٍ م</i>ُّب<i class=tj-madd>ِي</i>نٍ","25":"قُل لَّا تُسْــَٔلُونَ عَ<i class=tj-ghunnah>مّ</i><i class=tj-madd>َآ</i> أَ<i class=tj-qalqalah>جْ</i>رَمْنَا وَلَا نُسْــَٔلُ عَ<i class=tj-ghunnah>مّ</i>َا تَعْمَل<i class=tj-madd>ُو</i>نَ","26":"قُلْ يَ<i class=tj-qalqalah>جْ</i>مَعُ بَيْنَنَا رَبُّنَا ثُ<i class=tj-ghunnah>مّ</i>َ يَفْتَحُ بَيْنَنَا بِ<i class=tj-silent>ٱ</i>لْحَقِّ وَهُوَ <i class=tj-silent>ٱ</i>لْفَتَّاحُ <i class=tj-silent>ٱ</i>لْعَل<i class=tj-madd>ِي</i>مُ","27":"قُلْ أَرُونِىَ <i class=tj-silent>ٱ</i>لَّذِينَ أَلْحَ<i class=tj-qalqalah>قْ</i>ت<i class=tj-ikhfa>ُم ب</i>ِه<i class=tj-madd>ِۦ</i> شُرَك<i class=tj-madd>َا</i>ٓءَۖ كَلَّاۚ بَلْ هُوَ <i class=tj-silent>ٱ</i>للَّهُ <i class=tj-silent>ٱ</i>لْعَزِيزُ <i class=tj-silent>ٱ</i>لْحَك<i class=tj-madd>ِي</i>مُ","28":"وَم<i class=tj-madd>َآ</i> أَرْسَلْنَ<i class=tj-madd>ـٰ</i>كَ إِلَّا ك<i class=tj-madd>َا</i>ٓفَّ<i class=tj-silent>ةً ل</i>ِّل<i class=tj-ghunnah>نّ</i>َاسِ بَشِي<i class=tj-ghunnah>رًا و</i>َنَذِي<i class=tj-ghunnah>رًا و</i>َلَ<i class=tj-madd>ـٰ</i>كِ<i class=tj-ghunnah>نّ</i>َ أَكْثَرَ <i class=tj-silent>ٱ</i><i class=tj-silent>ل</i><i class=tj-ghunnah>نّ</i>َاسِ لَا يَعْلَم<i class=tj-madd>ُو</i>نَ","29":"وَيَقُولُونَ مَتَىٰ هَ<i class=tj-madd>ـٰ</i>ذَا <i class=tj-silent>ٱ</i>لْوَعْدُ إِ<i class=tj-ikhfa>ن ك</i>ُ<i class=tj-ikhfa>نت</i>ُمْ صَ<i class=tj-madd>ـٰ</i>دِق<i class=tj-madd>ِي</i>نَ","30":"قُل لَّك<i class=tj-ghunnah>ُم م</i>ِّيعَادُ يَوْ<i class=tj-silent>مٍ ل</i>َّا تَسْتَــْٔخِرُونَ عَنْهُ سَاعَ<i class=tj-ghunnah>ةً و</i>َلَا تَسْتَ<i class=tj-qalqalah>قْ</i>دِم<i class=tj-madd>ُو</i>نَ","31":"وَقَالَ <i class=tj-silent>ٱ</i>لَّذِينَ كَفَرُو<i class=tj-silent>اْ</i> ل<i class=tj-ghunnah>َن ن</i>ُّؤْمِنَ بِهَ<i class=tj-madd>ـٰ</i>ذَا <i class=tj-silent>ٱ</i>لْقُرْءَانِ وَلَا بِ<i class=tj-silent>ٱ</i>لَّذِى بَيْنَ يَدَيْهِۗ وَلَوْ تَرَ<i class=tj-madd>ىٰٓ</i> إِذِ <i class=tj-silent>ٱ</i><i class=tj-silent>ل</i>ظَّ<i class=tj-madd>ـٰ</i>لِمُونَ مَوْقُوفُونَ عِ<i class=tj-ikhfa>ند</i>َ رَبِّهِمْ يَرْجِعُ بَعْضُهُمْ إِلَىٰ بَعْضٍ <i class=tj-silent>ٱ</i>لْقَوْلَ يَقُولُ <i class=tj-silent>ٱ</i>لَّذِينَ <i class=tj-silent>ٱ</i>سْتُضْعِفُو<i class=tj-silent>اْ</i> لِلَّذِينَ <i class=tj-silent>ٱ</i>سْتَكْبَرُو<i class=tj-silent>اْ</i> لَوْل<i class=tj-madd>َآ</i> أَ<i class=tj-ikhfa>نت</i>ُمْ لَكُ<i class=tj-ghunnah>نّ</i>َا مُؤْمِن<i class=tj-madd>ِي</i>نَ","32":"قَالَ <i class=tj-silent>ٱ</i>لَّذِينَ <i class=tj-silent>ٱ</i>سْتَكْبَرُو<i class=tj-silent>اْ</i> لِلَّذِينَ <i class=tj-silent>ٱ</i>سْتُضْعِف<i class=tj-madd>ُوٓ</i><i class=tj-silent>اْ</i> أَنَحْنُ صَدَ<i class=tj-qalqalah>دْ</i>نَ<i class=tj-madd>ـٰ</i>كُمْ عَنِ <i class=tj-silent>ٱ</i>لْهُدَىٰ بَعْدَ إِذْ ج<i class=tj-madd>َا</i>ٓءَك<i class=tj-ikhfa>ُمۖ ب</i>َلْ كُ<i class=tj-ikhfa>نت</i><i class=tj-ghunnah>ُم م</i>ُّ<i class=tj-qalqalah>جْ</i>رِم<i class=tj-madd>ِي</i>نَ","33":"وَقَالَ <i class=tj-silent>ٱ</i>لَّذِينَ <i class=tj-silent>ٱ</i>سْتُضْعِفُو<i class=tj-silent>اْ</i> لِلَّذِينَ <i class=tj-silent>ٱ</i>سْتَكْبَرُو<i class=tj-silent>اْ</i> بَلْ مَكْرُ <i class=tj-silent>ٱ</i>لَّيْلِ وَ<i class=tj-silent>ٱ</i><i class=tj-silent>ل</i><i class=tj-ghunnah>نّ</i>َهَارِ إِذْ تَأْمُرُونَن<i class=tj-madd>َآ</i> أ<i class=tj-ghunnah>َن ن</i>َّكْفُرَ بِ<i class=tj-silent>ٱ</i>للَّهِ وَنَ<i class=tj-qalqalah>جْ</i>عَلَ لَهُ<i class=tj-madd>ۥٓ</i> أَ<i class=tj-ikhfa>ند</i>َا<i class=tj-ghunnah>دًاۚ و</i>َأَسَرُّو<i class=tj-silent>اْ</i> <i class=tj-silent>ٱ</i><i class=tj-silent>ل</i><i class=tj-ghunnah>نّ</i>َدَامَةَ لَ<i class=tj-ghunnah>مّ</i>َا رَأَوُ<i class=tj-silent>اْ</i> <i class=tj-silent>ٱ</i>لْعَذَابَ وَجَعَلْنَا <i class=tj-silent>ٱ</i>لْأَغْلَ<i class=tj-madd>ـٰ</i>لَ ف<i class=tj-madd>ِىٓ</i> أَعْنَاقِ <i class=tj-silent>ٱ</i>لَّذِينَ كَفَرُو<i class=tj-silent>اْۚ</i> هَلْ يُ<i class=tj-qalqalah>جْ</i>زَوْنَ إِلَّا مَا كَانُو<i class=tj-silent>اْ</i> يَعْمَل<i class=tj-madd>ُو</i>نَ","34":"وَم<i class=tj-madd>َآ</i> أَرْسَلْنَا فِى قَرْيَ<i class=tj-ghunnah>ةٍ م</i>ّ<i class=tj-ghunnah>ِن ن</i>َّذِيرٍ إِلَّا قَالَ مُتْرَفُوه<i class=tj-madd>َآ</i> إِ<i class=tj-ghunnah>نّ</i>َا بِم<i class=tj-madd>َآ</i> أُرْسِلْت<i class=tj-ikhfa>ُم ب</i>ِه<i class=tj-madd>ِۦ</i> كَ<i class=tj-madd>ـٰ</i>فِر<i class=tj-madd>ُو</i>نَ","35":"وَقَالُو<i class=tj-silent>اْ</i> نَحْنُ أَكْثَرُ أَمْو<i class=tj-madd>َٲ</i>ل<i class=tj-ghunnah>اً و</i>َأَوْلَ<i class=tj-madd>ـٰ</i><i class=tj-ghunnah>دًا و</i>َمَا نَحْنُ بِمُعَذَّب<i class=tj-madd>ِي</i>نَ","36":"قُلْ إِ<i class=tj-ghunnah>نّ</i>َ رَبِّى يَ<i class=tj-qalqalah>بْ</i>سُطُ <i class=tj-silent>ٱ</i><i class=tj-silent>ل</i>رِّزْقَ لِم<i class=tj-ghunnah>َن ي</i>َش<i class=tj-madd>َا</i>ٓءُ وَيَ<i class=tj-qalqalah>قْ</i>دِرُ وَلَ<i class=tj-madd>ـٰ</i>كِ<i class=tj-ghunnah>نّ</i>َ أَكْثَرَ <i class=tj-silent>ٱ</i><i class=tj-silent>ل</i><i class=tj-ghunnah>نّ</i>َاسِ لَا يَعْلَم<i class=tj-madd>ُو</i>نَ","37":"وَم<i class=tj-madd>َآ</i> أَمْو<i class=tj-madd>َٲ</i>لُكُمْ وَل<i class=tj-madd>َآ</i> أَوْلَ<i class=tj-madd>ـٰ</i>دُك<i class=tj-ikhfa>ُم ب</i>ِ<i class=tj-silent>ٱ</i>لَّتِى تُقَرِّبُكُمْ عِ<i class=tj-ikhfa>ند</i>َنَا زُلْفَ<i class=tj-madd>ىٰٓ</i> إِلَّا مَنْ ءَامَنَ وَعَمِلَ صَ<i class=tj-madd>ـٰ</i>لِ<i class=tj-ikhfa>حًا ف</i>َأُ<i class=tj-silent>وْ</i>لَ<i class=tj-madd>ـٰٓ</i>ئِكَ لَهُمْ جَز<i class=tj-madd>َا</i>ٓءُ <i class=tj-silent>ٱ</i><i class=tj-silent>ل</i>ضِّعْفِ بِمَا عَمِلُو<i class=tj-silent>اْ</i> وَهُمْ فِى <i class=tj-silent>ٱ</i>لْغُرُفَ<i class=tj-madd>ـٰ</i>تِ ءَامِن<i class=tj-madd>ُو</i>نَ","38":"وَ<i class=tj-silent>ٱ</i>لَّذِينَ يَسْعَوْنَ ف<i class=tj-madd>ِىٓ</i> ءَايَ<i class=tj-madd>ـٰ</i>تِنَا مُعَ<i class=tj-madd>ـٰ</i>جِزِينَ أُ<i class=tj-silent>وْ</i>لَ<i class=tj-madd>ـٰٓ</i>ئِكَ فِى <i class=tj-silent>ٱ</i>لْعَذَابِ مُحْضَر<i class=tj-madd>ُو</i>نَ","39":"قُلْ إِ<i class=tj-ghunnah>نّ</i>َ رَبِّى يَ<i class=tj-qalqalah>بْ</i>سُطُ <i class=tj-silent>ٱ</i><i class=tj-silent>ل</i>رِّزْقَ لِم<i class=tj-ghunnah>َن ي</i>َش<i class=tj-madd>َا</i>ٓءُ مِنْ عِبَادِه<i class=tj-madd>ِۦ</i> وَيَ<i class=tj-qalqalah>قْ</i>دِرُ لَهُ<i class=tj-madd>ۥ</i>ۚ وَم<i class=tj-madd>َآ</i> أَ<i class=tj-ikhfa>نف</i>َ<i class=tj-qalqalah>قْ</i>ت<i class=tj-ghunnah>ُم م</i>ِّ<i class=tj-ikhfa>ن ش</i><i class=tj-ikhfa>َىْءٍ ف</i>َهُوَ يُخْلِفُهُۖ<i class=tj-madd>ۥ</i> وَهُوَ خَيْرُ <i class=tj-silent>ٱ</i><i class=tj-silent>ل</i>رّ<i class=tj-madd>َٲ</i>زِق<i class=tj-madd>ِي</i>نَ","40":"وَيَوْمَ يَحْشُرُهُمْ جَمِي<i class=tj-ikhfa>عًا ث</i>ُ<i class=tj-ghunnah>مّ</i>َ يَقُولُ لِلْمَلَ<i class=tj-madd>ـٰٓ</i>ئِكَةِ أَهَ<i class=tj-madd>ـٰٓ</i>ؤُل<i class=tj-madd>َا</i>ٓءِ إِيَّاكُمْ كَانُو<i class=tj-silent>اْ</i> يَعْبُد<i class=tj-madd>ُو</i>نَ","41":"قَالُو<i class=tj-silent>اْ</i> سُ<i class=tj-qalqalah>بْ</i>حَ<i class=tj-madd>ـٰ</i>نَكَ أَ<i class=tj-ikhfa>نت</i>َ وَلِيُّنَا مِ<i class=tj-ikhfa>ن د</i>ُونِه<i class=tj-ikhfa>ِمۖ ب</i>َلْ كَانُو<i class=tj-silent>اْ</i> يَعْبُدُونَ <i class=tj-silent>ٱ</i>لْجِ<i class=tj-ghunnah>نّ</i>َۖ أَكْثَرُه<i class=tj-ikhfa>ُم ب</i>ِه<i class=tj-ghunnah>ِم م</i>ُّؤْمِن<i class=tj-madd>ُو</i>نَ","42":"فَ<i class=tj-silent>ٱ</i>لْيَوْمَ لَا يَمْلِكُ بَعْضُكُمْ لِبَعْ<i class=tj-ghunnah>ضٍ ن</i>َّفْ<i class=tj-ghunnah>عًا و</i>َلَا ضَر<i class=tj-ghunnah>ًّا و</i>َنَقُولُ لِلَّذِينَ ظَلَمُو<i class=tj-silent>اْ</i> ذُوقُو<i class=tj-silent>اْ</i> عَذَابَ <i class=tj-silent>ٱ</i><i class=tj-silent>ل</i><i class=tj-ghunnah>نّ</i>َارِ <i class=tj-silent>ٱ</i>لَّتِى كُ<i class=tj-ikhfa>نت</i><i class=tj-ikhfa>ُم ب</i>ِهَا تُكَذِّب<i class=tj-madd>ُو</i>نَ","43":"وَإِذَا تُتْلَىٰ عَلَيْهِمْ ءَايَ<i class=tj-madd>ـٰ</i>تُنَا بَيِّنَ<i class=tj-madd>ـٰ</i><i class=tj-ikhfa>تٍ ق</i>َالُو<i class=tj-silent>اْ</i> مَا هَ<i class=tj-madd>ـٰ</i>ذ<i class=tj-madd>َآ</i> إِلَّا رَجُ<i class=tj-ghunnah>لٌ ي</i>ُرِيدُ أ<i class=tj-ghunnah>َن ي</i>َصُدَّكُمْ عَ<i class=tj-ghunnah>مّ</i>َا كَانَ يَعْبُدُ ءَاب<i class=tj-madd>َا</i>ٓؤُكُمْ وَقَالُو<i class=tj-silent>اْ</i> مَا هَ<i class=tj-madd>ـٰ</i>ذ<i class=tj-madd>َآ</i> إِلّ<i class=tj-madd>َآ</i> إِفْ<i class=tj-ghunnah>كٌ م</i>ُّفْتَ<i class=tj-ghunnah>رًىۚ و</i>َقَالَ <i class=tj-silent>ٱ</i>لَّذِينَ كَفَرُو<i class=tj-silent>اْ</i> لِلْحَقِّ لَ<i class=tj-ghunnah>مّ</i>َا ج<i class=tj-madd>َا</i>ٓءَهُمْ إِنْ هَ<i class=tj-madd>ـٰ</i>ذ<i class=tj-madd>َآ</i> إِلَّا سِحْ<i class=tj-ghunnah>رٌ م</i>ُّب<i class=tj-madd>ِي</i>نٌ","44":"وَم<i class=tj-madd>َآ</i> ءَاتَيْنَ<i class=tj-madd>ـٰ</i>ه<i class=tj-ghunnah>ُم م</i>ِّ<i class=tj-ikhfa>ن ك</i>ُتُ<i class=tj-ghunnah>بٍ ي</i>َ<i class=tj-qalqalah>دْ</i>رُسُونَهَاۖ وَم<i class=tj-madd>َآ</i> أَرْسَلْن<i class=tj-madd>َآ</i> إِلَيْهِمْ قَ<i class=tj-qalqalah>بْ</i>لَكَ م<i class=tj-ghunnah>ِن ن</i>َّذ<i class=tj-madd>ِي</i>رٍ","45":"وَكَذَّبَ <i class=tj-silent>ٱ</i>لَّذِينَ مِ<i class=tj-ikhfa>ن ق</i>َ<i class=tj-qalqalah>بْ</i>لِهِمْ وَمَا بَلَغُو<i class=tj-silent>اْ</i> مِعْشَارَ م<i class=tj-madd>َآ</i> ءَاتَيْنَ<i class=tj-madd>ـٰ</i>هُمْ فَكَذَّبُو<i class=tj-silent>اْ</i> رُسُلِىۖ فَكَيْفَ كَانَ نَك<i class=tj-madd>ِي</i>رِ","46":"۞ قُلْ إِ<i class=tj-ghunnah>نّ</i>َم<i class=tj-madd>َآ</i> أَعِظُك<i class=tj-ikhfa>ُم ب</i>ِو<i class=tj-madd>َٲ</i>حِدَةٍۖ أَ<i class=tj-ikhfa>ن ت</i>َقُومُو<i class=tj-silent>اْ</i> لِلَّهِ مَثْنَىٰ وَفُر<i class=tj-madd>َٲ</i>دَىٰ ثُ<i class=tj-ghunnah>مّ</i>َ تَتَفَكَّرُو<i class=tj-silent>اْۚ</i> مَا بِصَاحِبِك<i class=tj-ghunnah>ُم م</i>ِّ<i class=tj-ikhfa>ن ج</i>ِ<i class=tj-ghunnah>نّ</i>َةٍۚ إِنْ هُوَ إِلَّا نَذِي<i class=tj-silent>رٌ ل</i>َّك<i class=tj-ikhfa>ُم ب</i>َيْنَ يَدَىْ عَذَا<i class=tj-ikhfa>بٍ ش</i>َد<i class=tj-madd>ِي</i><i class=tj-qalqalah>د</i>ٍ","47":"قُلْ مَا سَأَلْتُك<i class=tj-ghunnah>ُم م</i>ِّنْ أَ<i class=tj-qalqalah>جْ</i><i class=tj-ikhfa>رٍ ف</i>َهُوَ لَكُمْۖ إِنْ أَ<i class=tj-qalqalah>جْ</i>رِىَ إِلَّا عَلَى <i class=tj-silent>ٱ</i>للَّهِۖ وَهُوَ عَلَىٰ كُلِّ ش<i class=tj-ikhfa>َىْءٍ ش</i>َه<i class=tj-madd>ِي</i><i class=tj-qalqalah>د</i>ٌ","48":"قُلْ إِ<i class=tj-ghunnah>نّ</i>َ رَبِّى يَ<i class=tj-qalqalah>قْ</i>ذِفُ بِ<i class=tj-silent>ٱ</i>لْحَقِّ عَلَّ<i class=tj-madd>ـٰ</i>مُ <i class=tj-silent>ٱ</i>لْغُي<i class=tj-madd>ُو</i><i class=tj-qalqalah>ب</i>ِ","49":"قُلْ ج<i class=tj-madd>َا</i>ٓءَ <i class=tj-silent>ٱ</i>لْحَقُّ وَمَا يُ<i class=tj-qalqalah>بْ</i>دِئُ <i class=tj-silent>ٱ</i>لْبَ<i class=tj-madd>ـٰ</i>طِلُ وَمَا يُع<i class=tj-madd>ِي</i><i class=tj-qalqalah>د</i>ُ","50":"قُلْ إِ<i class=tj-ikhfa>ن ض</i>َلَلْتُ فَإِ<i class=tj-ghunnah>نّ</i>َم<i class=tj-madd>َآ</i> أَضِلُّ عَلَىٰ نَفْسِىۖ وَإِنِ <i class=tj-silent>ٱ</i>هْتَدَيْتُ فَبِمَا يُوح<i class=tj-madd>ِىٓ</i> إِلَىَّ رَبّ<i class=tj-madd>ِىٓۚ</i> إِ<i class=tj-ghunnah>نّ</i>َهُ<i class=tj-madd>ۥ</i> سَمِي<i class=tj-ikhfa>عٌ ق</i>َر<i class=tj-madd>ِي</i><i class=tj-qalqalah>ب</i>ٌ","51":"وَلَوْ تَرَ<i class=tj-madd>ىٰٓ</i> إِذْ فَزِعُو<i class=tj-silent>اْ</i> فَلَا فَوْتَ وَأُخِذُو<i class=tj-silent>اْ</i> م<i class=tj-ghunnah>ِن م</i>َّكَا<i class=tj-ikhfa>نٍ ق</i>َر<i class=tj-madd>ِي</i><i class=tj-qalqalah>ب</i>ٍ","52":"وَقَال<i class=tj-madd>ُوٓ</i><i class=tj-silent>اْ</i> ءَامَ<i class=tj-ghunnah>نّ</i>َا بِه<i class=tj-madd>ِۦ</i> وَأَ<i class=tj-ghunnah>نّ</i>َىٰ لَهُمُ <i class=tj-silent>ٱ</i><i class=tj-silent>ل</i>تَّنَاوُشُ م<i class=tj-ghunnah>ِن م</i>َّكَا<i class=tj-ikhfa>نِۭ ب</i>َع<i class=tj-madd>ِي</i><i class=tj-qalqalah>د</i>ٍ","53":"وَقَ<i class=tj-qalqalah>دْ</i> كَفَرُو<i class=tj-silent>اْ</i> بِه<i class=tj-madd>ِۦ</i> مِ<i class=tj-ikhfa>ن ق</i>َ<i class=tj-qalqalah>بْ</i>لُۖ وَيَ<i class=tj-qalqalah>قْ</i>ذِفُونَ بِ<i class=tj-silent>ٱ</i>لْغَيْبِ م<i class=tj-ghunnah>ِن م</i>َّكَا<i class=tj-ikhfa>نِۭ ب</i>َع<i class=tj-madd>ِي</i><i class=tj-qalqalah>د</i>ٍ","54":"وَحِيلَ بَيْنَهُمْ وَبَيْنَ مَا يَشْتَهُونَ كَمَا فُعِلَ بِأَشْيَاعِه<i class=tj-ghunnah>ِم م</i>ِّ<i class=tj-ikhfa>ن ق</i>َ<i class=tj-qalqalah>بْ</i>لُۚ إِ<i class=tj-ghunnah>نّ</i>َهُمْ كَانُو<i class=tj-silent>اْ</i> فِى شَ<i class=tj-ghunnah>كٍّ م</i>ُّر<i class=tj-madd>ِي</i><i class=tj-qalqalah>ب</i>ِۭ"}}