{"verses":{"1":"إِذَا <i class=tj-silent>ٱ</i><i class=tj-silent>ل</i>سَّم<i class=tj-madd>َا</i>ٓءُ <i class=tj-silent>ٱ</i><i class=tj-ikhfa>نف</i>َطَرَتْ","2":"وَإِذَا <i class=tj-silent>ٱ</i>لْكَوَاكِبُ <i class=tj-silent>ٱ</i><i class=tj-ikhfa>نت</i>َثَرَتْ","3":"وَإِذَا <i class=tj-silent>ٱ</i>لْبِحَارُ فُجِّرَتْ","4":"وَإِذَا <i class=tj-silent>ٱ</i>لْقُبُورُ بُعْثِرَتْ","5":"عَلِمَتْ نَفْ<i class=tj-ghunnah>سٌ م</i>َّا قَدَّمَتْ وَأَخَّرَتْ","6":"يَ<i class=tj-madd>ـٰٓ</i>أَيُّهَا <i class=tj-silent>ٱ</i>لْإِ<i class=tj-ikhfa>نس</i>َ<i class=tj-madd>ـٰ</i>نُ مَا غَرَّكَ بِرَبِّكَ <i class=tj-silent>ٱ</i>لْكَر<i class=tj-madd>ِي</i>مِ","7":"ٱلَّذِى خَلَقَكَ فَسَوَّ<i class=tj-madd>ٮٰ</i>كَ فَعَدَلَكَ","8":"ف<i class=tj-madd>ِىٓ</i> أَىِّ صُورَ<i class=tj-ghunnah>ةٍ م</i>َّا ش<i class=tj-madd>َا</i>ٓءَ رَكَّبَكَ","9":"كَلَّا بَلْ تُكَذِّبُونَ بِ<i class=tj-silent>ٱ</i><i class=tj-silent>ل</i>دّ<i class=tj-madd>ِي</i>نِ","10":"وَإِ<i class=tj-ghunnah>نّ</i>َ عَلَيْكُمْ لَحَ<i class=tj-madd>ـٰ</i>فِظ<i class=tj-madd>ِي</i>نَ","11":"كِرَا<i class=tj-ikhfa>مًا ك</i>َ<i class=tj-madd>ـٰ</i>تِب<i class=tj-madd>ِي</i>نَ","12":"يَعْلَمُونَ مَا تَفْعَل<i class=tj-madd>ُو</i>نَ","13":"إِ<i class=tj-ghunnah>نّ</i>َ <i class=tj-silent>ٱ</i>لْأَ<i class=tj-qalqalah>بْ</i>رَارَ لَفِى نَع<i class=tj-madd>ِي</i>مٍ","14":"وَإِ<i class=tj-ghunnah>نّ</i>َ <i class=tj-silent>ٱ</i>لْفُجَّارَ لَفِى جَح<i class=tj-madd>ِي</i>مٍ","15":"يَصْلَوْنَهَا يَوْمَ <i class=tj-silent>ٱ</i><i class=tj-silent>ل</i>دّ<i class=tj-madd>ِي</i>نِ","16":"وَمَا هُمْ عَنْهَا بِغ<i class=tj-madd>َا</i>ٓئِب<i class=tj-madd>ِي</i>نَ","17":"وَم<i class=tj-madd>َآ</i> أَ<i class=tj-qalqalah>دْ</i>رَ<i class=tj-madd>ٮٰ</i>كَ مَا يَوْمُ <i class=tj-silent>ٱ</i><i class=tj-silent>ل</i>دّ<i class=tj-madd>ِي</i>نِ","18":"ثُ<i class=tj-ghunnah>مّ</i>َ م<i class=tj-madd>َآ</i> أَ<i class=tj-qalqalah>دْ</i>رَ<i class=tj-madd>ٮٰ</i>كَ مَا يَوْمُ <i class=tj-silent>ٱ</i><i class=tj-silent>ل</i>دّ<i class=tj-madd>ِي</i>نِ","19":"يَوْمَ لَا تَمْلِكُ نَفْ<i class=tj-silent>سٌ ل</i>ِّنَفْ<i class=tj-ikhfa>سٍ ش</i>َيْـ<i class=tj-ghunnah>ـًٔا‌ۖ و</i>َ<i class=tj-silent>ٱ</i>لْأَمْرُ يَوْمَئِ<i class=tj-silent>ذٍ ل</i>ِّلَّهِ"}}