{"verses":{"1":"ا<i class=tj-madd>لٓ</i><i class=tj-madd>مٓ</i>","2":"أَحَسِبَ <i class=tj-silent>ٱ</i><i class=tj-silent>ل</i><i class=tj-ghunnah>نّ</i>َاسُ أ<i class=tj-ghunnah>َن ي</i>ُتْرَك<i class=tj-madd>ُوٓ</i><i class=tj-silent>اْ</i> أ<i class=tj-ghunnah>َن ي</i>َقُول<i class=tj-madd>ُوٓ</i><i class=tj-silent>اْ</i> ءَامَ<i class=tj-ghunnah>نّ</i>َا وَهُمْ لَا يُفْتَن<i class=tj-madd>ُو</i>نَ","3":"وَلَقَ<i class=tj-qalqalah>دْ</i> فَتَ<i class=tj-ghunnah>نّ</i>َا <i class=tj-silent>ٱ</i>لَّذِينَ مِ<i class=tj-ikhfa>ن ق</i>َ<i class=tj-qalqalah>بْ</i>لِهِمْ‌ۖ فَلَيَعْلَمَ<i class=tj-ghunnah>نّ</i>َ <i class=tj-silent>ٱ</i>للَّهُ <i class=tj-silent>ٱ</i>لَّذِينَ صَدَقُو<i class=tj-silent>اْ</i> وَلَيَعْلَمَ<i class=tj-ghunnah>نّ</i>َ <i class=tj-silent>ٱ</i>لْكَ<i class=tj-madd>ـٰ</i>ذِب<i class=tj-madd>ِي</i>نَ","4":"أَمْ حَسِبَ <i class=tj-silent>ٱ</i>لَّذِينَ يَعْمَلُونَ <i class=tj-silent>ٱ</i><i class=tj-silent>ل</i>سَّيِّـَٔـاتِ أ<i class=tj-ghunnah>َن ي</i>َسْبِقُونَا‌ۚ س<i class=tj-madd>َا</i>ٓءَ مَا يَحْكُم<i class=tj-madd>ُو</i>نَ","5":"مَ<i class=tj-ikhfa>ن ك</i>َانَ يَرْجُو<i class=tj-silent>اْ</i> لِق<i class=tj-madd>َا</i>ٓءَ <i class=tj-silent>ٱ</i>للَّهِ فَإِ<i class=tj-ghunnah>نّ</i>َ أَجَلَ <i class=tj-silent>ٱ</i>للَّهِ لَأَ<i class=tj-ghunnah>تٍ‌ۚ و</i>َهُوَ <i class=tj-silent>ٱ</i><i class=tj-silent>ل</i>سَّمِيعُ <i class=tj-silent>ٱ</i>لْعَل<i class=tj-madd>ِي</i>مُ","6":"وَمَ<i class=tj-ikhfa>ن ج</i>َ<i class=tj-madd>ـٰ</i>هَدَ فَإِ<i class=tj-ghunnah>نّ</i>َمَا يُجَ<i class=tj-madd>ـٰ</i>هِدُ لِنَفْسِه<i class=tj-madd>ِۦٓ‌ۚ</i> إِ<i class=tj-ghunnah>نّ</i>َ <i class=tj-silent>ٱ</i>للَّهَ لَغَنِىٌّ عَنِ <i class=tj-silent>ٱ</i>لْعَ<i class=tj-madd>ـٰ</i>لَم<i class=tj-madd>ِي</i>نَ","7":"وَ<i class=tj-silent>ٱ</i>لَّذِينَ ءَامَنُو<i class=tj-silent>اْ</i> وَعَمِلُو<i class=tj-silent>اْ</i> <i class=tj-silent>ٱ</i><i class=tj-silent>ل</i>صَّ<i class=tj-madd>ـٰ</i>لِحَ<i class=tj-madd>ـٰ</i>تِ لَنُكَفِّرَ<i class=tj-ghunnah>نّ</i>َ عَنْهُمْ سَيِّـَٔـاتِهِمْ وَلَنَ<i class=tj-qalqalah>جْ</i>زِيَ<i class=tj-ghunnah>نّ</i>َهُمْ أَحْسَنَ <i class=tj-silent>ٱ</i>لَّذِى كَانُو<i class=tj-silent>اْ</i> يَعْمَل<i class=tj-madd>ُو</i>نَ","8":"وَوَصَّيْنَا <i class=tj-silent>ٱ</i>لْإِ<i class=tj-ikhfa>نس</i>َ<i class=tj-madd>ـٰ</i>نَ بِو<i class=tj-madd>َٲ</i>لِدَيْهِ حُسْ<i class=tj-ghunnah>نًا‌ۖ و</i>َإِ<i class=tj-ikhfa>ن ج</i>َ<i class=tj-madd>ـٰ</i>هَدَاكَ لِتُشْرِكَ بِى مَا لَيْسَ لَكَ بِه<i class=tj-madd>ِۦ</i> عِلْ<i class=tj-ikhfa>مٌ ف</i>َلَا تُطِعْهُم<i class=tj-madd>َآ‌ۚ</i> إِلَىَّ مَرْجِعُكُمْ فَأُنَبِّئُك<i class=tj-ikhfa>ُم ب</i>ِمَا كُ<i class=tj-ikhfa>نت</i>ُمْ تَعْمَل<i class=tj-madd>ُو</i>نَ","9":"وَ<i class=tj-silent>ٱ</i>لَّذِينَ ءَامَنُو<i class=tj-silent>اْ</i> وَعَمِلُو<i class=tj-silent>اْ</i> <i class=tj-silent>ٱ</i><i class=tj-silent>ل</i>صَّ<i class=tj-madd>ـٰ</i>لِحَ<i class=tj-madd>ـٰ</i>تِ لَنُ<i class=tj-qalqalah>دْ</i>خِلَ<i class=tj-ghunnah>نّ</i>َهُمْ فِى <i class=tj-silent>ٱ</i><i class=tj-silent>ل</i>صَّ<i class=tj-madd>ـٰ</i>لِح<i class=tj-madd>ِي</i>نَ","10":"وَمِنَ <i class=tj-silent>ٱ</i><i class=tj-silent>ل</i><i class=tj-ghunnah>نّ</i>َاسِ م<i class=tj-ghunnah>َن ي</i>َقُولُ ءَامَ<i class=tj-ghunnah>نّ</i>َا بِ<i class=tj-silent>ٱ</i>للَّهِ فَإِذ<i class=tj-madd>َآ</i> أُوذِىَ فِى <i class=tj-silent>ٱ</i>للَّهِ جَعَلَ فِتْنَةَ <i class=tj-silent>ٱ</i><i class=tj-silent>ل</i><i class=tj-ghunnah>نّ</i>َاسِ كَعَذَابِ <i class=tj-silent>ٱ</i>للَّهِ وَلَئِ<i class=tj-ikhfa>ن ج</i><i class=tj-madd>َا</i>ٓءَ نَصْ<i class=tj-ghunnah>رٌ م</i>ّ<i class=tj-silent>ِن ر</i>َّبِّكَ لَيَقُولُ<i class=tj-ghunnah>نّ</i>َ إِ<i class=tj-ghunnah>نّ</i>َا كُ<i class=tj-ghunnah>نّ</i>َا مَعَكُمْ‌ۚ أَوَلَيْسَ <i class=tj-silent>ٱ</i>للَّهُ بِأَعْلَمَ بِمَا فِى صُدُورِ <i class=tj-silent>ٱ</i>لْعَ<i class=tj-madd>ـٰ</i>لَم<i class=tj-madd>ِي</i>نَ","11":"وَلَيَعْلَمَ<i class=tj-ghunnah>نّ</i>َ <i class=tj-silent>ٱ</i>للَّهُ <i class=tj-silent>ٱ</i>لَّذِينَ ءَامَنُو<i class=tj-silent>اْ</i> وَلَيَعْلَمَ<i class=tj-ghunnah>نّ</i>َ <i class=tj-silent>ٱ</i>لْمُنَ<i class=tj-madd>ـٰ</i>فِق<i class=tj-madd>ِي</i>نَ","12":"وَقَالَ <i class=tj-silent>ٱ</i>لَّذِينَ كَفَرُو<i class=tj-silent>اْ</i> لِلَّذِينَ ءَامَنُو<i class=tj-silent>اْ</i> <i class=tj-silent>ٱ</i>تَّبِعُو<i class=tj-silent>اْ</i> سَبِيلَنَا وَلْنَحْمِلْ خَطَ<i class=tj-madd>ـٰ</i>يَ<i class=tj-madd>ـٰ</i>كُمْ وَمَا ه<i class=tj-ikhfa>ُم ب</i>ِحَ<i class=tj-madd>ـٰ</i>مِلِينَ مِنْ خَطَ<i class=tj-madd>ـٰ</i>يَ<i class=tj-madd>ـٰ</i>ه<i class=tj-ghunnah>ُم م</i>ِّ<i class=tj-ikhfa>ن ش</i>َىْءٍ‌ۖ إِ<i class=tj-ghunnah>نّ</i>َهُمْ لَكَ<i class=tj-madd>ـٰ</i>ذِب<i class=tj-madd>ُو</i>نَ","13":"وَلَيَحْمِلُ<i class=tj-ghunnah>نّ</i>َ أَثْقَالَهُمْ وَأَثْقَال<i class=tj-ghunnah>اً م</i>َّعَ أَثْقَالِهِمْ‌ۖ وَلَيُسْــَٔلُ<i class=tj-ghunnah>نّ</i>َ يَوْمَ <i class=tj-silent>ٱ</i>لْقِيَ<i class=tj-madd>ـٰ</i>مَةِ عَ<i class=tj-ghunnah>مّ</i>َا كَانُو<i class=tj-silent>اْ</i> يَفْتَر<i class=tj-madd>ُو</i>نَ","14":"وَلَقَ<i class=tj-qalqalah>دْ</i> أَرْسَلْنَا نُوحًا إِلَىٰ قَوْمِه<i class=tj-madd>ِۦ</i> فَلَبِثَ فِيهِمْ أَلْفَ سَنَةٍ إِلَّا خَمْسِينَ عَا<i class=tj-ikhfa>مًا ف</i>َأَخَذَهُمُ <i class=tj-silent>ٱ</i><i class=tj-silent>ل</i>طُّوفَانُ وَهُمْ ظَ<i class=tj-madd>ـٰ</i>لِم<i class=tj-madd>ُو</i>نَ","15":"فَأَ<i class=tj-ikhfa>نج</i>َيْنَ<i class=tj-madd>ـٰ</i>هُ وَأَصْحَ<i class=tj-madd>ـٰ</i>بَ <i class=tj-silent>ٱ</i><i class=tj-silent>ل</i>سَّفِينَةِ وَجَعَلْنَ<i class=tj-madd>ـٰ</i>ه<i class=tj-madd>َآ</i> ءَايَ<i class=tj-silent>ةً ل</i>ِّلْعَ<i class=tj-madd>ـٰ</i>لَم<i class=tj-madd>ِي</i>نَ","16":"وَإِ<i class=tj-qalqalah>بْ</i>ر<i class=tj-madd>َٲ</i>هِيمَ إِذْ قَالَ لِقَوْمِهِ <i class=tj-silent>ٱ</i>عْبُدُو<i class=tj-silent>اْ</i> <i class=tj-silent>ٱ</i>للَّهَ وَ<i class=tj-silent>ٱ</i>تَّقُوهُ‌ۖ ذ<i class=tj-madd>َٲ</i>لِكُمْ خَيْ<i class=tj-silent>رٌ ل</i>َّكُمْ إِ<i class=tj-ikhfa>ن ك</i>ُ<i class=tj-ikhfa>نت</i>ُمْ تَعْلَم<i class=tj-madd>ُو</i>نَ","17":"إِ<i class=tj-ghunnah>نّ</i>َمَا تَعْبُدُونَ مِ<i class=tj-ikhfa>ن د</i>ُونِ <i class=tj-silent>ٱ</i>للَّهِ أَوْثَ<i class=tj-madd>ـٰ</i><i class=tj-ghunnah>نًا و</i>َتَخْلُقُونَ إِفْكًا‌ۚ إِ<i class=tj-ghunnah>نّ</i>َ <i class=tj-silent>ٱ</i>لَّذِينَ تَعْبُدُونَ مِ<i class=tj-ikhfa>ن د</i>ُونِ <i class=tj-silent>ٱ</i>للَّهِ لَا يَمْلِكُونَ لَكُمْ رِزْ<i class=tj-ikhfa>قًا ف</i>َ<i class=tj-silent>ٱ</i><i class=tj-qalqalah>بْ</i>تَغُو<i class=tj-silent>اْ</i> عِ<i class=tj-ikhfa>ند</i>َ <i class=tj-silent>ٱ</i>للَّهِ <i class=tj-silent>ٱ</i><i class=tj-silent>ل</i>رِّزْقَ وَ<i class=tj-silent>ٱ</i>عْبُدُوهُ وَ<i class=tj-silent>ٱ</i>شْكُرُو<i class=tj-silent>اْ</i> لَهُ<i class=tj-madd>ۥٓ‌ۖ</i> إِلَيْهِ تُرْجَع<i class=tj-madd>ُو</i>نَ","18":"وَإِ<i class=tj-ikhfa>ن ت</i>ُكَذِّبُو<i class=tj-silent>اْ</i> فَقَ<i class=tj-qalqalah>دْ</i> كَذَّبَ أُمَ<i class=tj-ghunnah>مٌ م</i>ِّ<i class=tj-ikhfa>ن ق</i>َ<i class=tj-qalqalah>بْ</i>لِكُمْ‌ۖ وَمَا عَلَى <i class=tj-silent>ٱ</i><i class=tj-silent>ل</i>رَّسُولِ إِلَّا <i class=tj-silent>ٱ</i>لْبَلَ<i class=tj-madd>ـٰ</i>غُ <i class=tj-silent>ٱ</i>لْمُب<i class=tj-madd>ِي</i>نُ","19":"أَوَلَمْ يَرَوْ<i class=tj-silent>اْ</i> كَيْفَ يُ<i class=tj-qalqalah>بْ</i>دِئُ <i class=tj-silent>ٱ</i>للَّهُ <i class=tj-silent>ٱ</i>لْخَلْقَ ثُ<i class=tj-ghunnah>مّ</i>َ يُعِيدُهُ<i class=tj-madd>ۥٓ‌ۚ</i> إِ<i class=tj-ghunnah>نّ</i>َ ذ<i class=tj-madd>َٲ</i>لِكَ عَلَى <i class=tj-silent>ٱ</i>للَّهِ يَس<i class=tj-madd>ِي</i>رٌ","20":"قُلْ سِيرُو<i class=tj-silent>اْ</i> فِى <i class=tj-silent>ٱ</i>لْأَرْضِ فَ<i class=tj-silent>ٱ</i><i class=tj-ikhfa>نظ</i>ُرُو<i class=tj-silent>اْ</i> كَيْفَ بَدَأَ <i class=tj-silent>ٱ</i>لْخَلْقَ‌ۚ ثُ<i class=tj-ghunnah>مّ</i>َ <i class=tj-silent>ٱ</i>للَّهُ يُ<i class=tj-ikhfa>نش</i>ِئُ <i class=tj-silent>ٱ</i><i class=tj-silent>ل</i><i class=tj-ghunnah>نّ</i>َشْأَةَ <i class=tj-silent>ٱ</i>لْأَخِرَةَ‌ۚ إِ<i class=tj-ghunnah>نّ</i>َ <i class=tj-silent>ٱ</i>للَّهَ عَلَىٰ كُلِّ ش<i class=tj-ikhfa>َىْءٍ ق</i>َد<i class=tj-madd>ِي</i>رٌ","21":"يُعَذِّبُ م<i class=tj-ghunnah>َن ي</i>َش<i class=tj-madd>َا</i>ٓءُ وَيَرْحَمُ م<i class=tj-ghunnah>َن ي</i>َش<i class=tj-madd>َا</i>ٓءُ‌ۖ وَإِلَيْهِ تُ<i class=tj-qalqalah>قْ</i>لَب<i class=tj-madd>ُو</i>نَ","22":"وَم<i class=tj-madd>َآ</i> أَ<i class=tj-ikhfa>نت</i><i class=tj-ikhfa>ُم ب</i>ِمُعْجِزِينَ فِى <i class=tj-silent>ٱ</i>لْأَرْضِ وَلَا فِى <i class=tj-silent>ٱ</i><i class=tj-silent>ل</i>سَّم<i class=tj-madd>َا</i>ٓءِ‌ۖ وَمَا لَك<i class=tj-ghunnah>ُم م</i>ِّ<i class=tj-ikhfa>ن د</i>ُونِ <i class=tj-silent>ٱ</i>للَّهِ م<i class=tj-ghunnah>ِن و</i>َلِ<i class=tj-ghunnah>ىٍّ و</i>َلَا نَص<i class=tj-madd>ِي</i>رٍ","23":"وَ<i class=tj-silent>ٱ</i>لَّذِينَ كَفَرُو<i class=tj-silent>اْ</i> بِـَٔـايَ<i class=tj-madd>ـٰ</i>تِ <i class=tj-silent>ٱ</i>للَّهِ وَلِق<i class=tj-madd>َا</i>ٓئِه<i class=tj-madd>ِۦٓ</i> أُ<i class=tj-silent>وْ</i>لَ<i class=tj-madd>ـٰٓ</i>ئِكَ يَئِسُو<i class=tj-silent>اْ</i> م<i class=tj-silent>ِن ر</i>َّحْمَتِى وَأُ<i class=tj-silent>وْ</i>لَ<i class=tj-madd>ـٰٓ</i>ئِكَ لَهُمْ عَذَابٌ أَل<i class=tj-madd>ِي</i>مٌ","24":"فَمَا كَانَ جَوَابَ قَوْمِه<i class=tj-madd>ِۦٓ</i> إِلّ<i class=tj-madd>َآ</i> أَ<i class=tj-ikhfa>ن ق</i>َالُو<i class=tj-silent>اْ</i> <i class=tj-silent>ٱ</i><i class=tj-qalqalah>قْ</i>تُلُوهُ أَوْ حَرِّقُوهُ فَأَ<i class=tj-ikhfa>نج</i>َ<i class=tj-madd>ـٰ</i>هُ <i class=tj-silent>ٱ</i>للَّهُ مِنَ <i class=tj-silent>ٱ</i><i class=tj-silent>ل</i><i class=tj-ghunnah>نّ</i>َارِ‌ۚ إِ<i class=tj-ghunnah>نّ</i>َ فِى ذ<i class=tj-madd>َٲ</i>لِكَ لَأَيَ<i class=tj-madd>ـٰ</i><i class=tj-silent>تٍ ل</i>ِّقَوْ<i class=tj-ghunnah>مٍ ي</i>ُؤْمِن<i class=tj-madd>ُو</i>نَ","25":"وَقَالَ إِ<i class=tj-ghunnah>نّ</i>َمَا <i class=tj-silent>ٱ</i>تَّخَذْت<i class=tj-ghunnah>ُم م</i>ِّ<i class=tj-ikhfa>ن د</i>ُونِ <i class=tj-silent>ٱ</i>للَّهِ أَوْثَ<i class=tj-madd>ـٰ</i><i class=tj-ghunnah>نًا م</i>َّوَدَّةَ بَيْنِكُمْ فِى <i class=tj-silent>ٱ</i>لْحَيَ<i class=tj-silent>و</i><i class=tj-madd>ٲ</i>ةِ <i class=tj-silent>ٱ</i><i class=tj-silent>ل</i>دُّنْيَا‌ۖ ثُ<i class=tj-ghunnah>مّ</i>َ يَوْمَ <i class=tj-silent>ٱ</i>لْقِيَ<i class=tj-madd>ـٰ</i>مَةِ يَكْفُرُ بَعْضُك<i class=tj-ikhfa>ُم ب</i>ِبَعْ<i class=tj-ghunnah>ضٍ و</i>َيَلْعَنُ بَعْضُك<i class=tj-ikhfa>ُم ب</i>َعْ<i class=tj-ghunnah>ضًا و</i>َمَأْوَ<i class=tj-madd>ٮٰ</i>كُمُ <i class=tj-silent>ٱ</i><i class=tj-silent>ل</i><i class=tj-ghunnah>نّ</i>َارُ وَمَا لَك<i class=tj-ghunnah>ُم م</i>ّ<i class=tj-ghunnah>ِن ن</i>َّ<i class=tj-madd>ـٰ</i>صِر<i class=tj-madd>ِي</i>نَ","26":"۞ فَـَٔـامَنَ لَهُ<i class=tj-madd>ۥ</i> لُو<i class=tj-ghunnah>طٌ‌ۘ و</i>َقَالَ إِ<i class=tj-ghunnah>نّ</i>ِى مُهَاجِرٌ إِلَىٰ رَبّ<i class=tj-madd>ِىٓ‌ۖ</i> إِ<i class=tj-ghunnah>نّ</i>َهُ<i class=tj-madd>ۥ</i> هُوَ <i class=tj-silent>ٱ</i>لْعَزِيزُ <i class=tj-silent>ٱ</i>لْحَك<i class=tj-madd>ِي</i>مُ","27":"وَوَهَ<i class=tj-qalqalah>بْ</i>نَا لَهُ<i class=tj-madd>ۥٓ</i> إِسْحَ<i class=tj-madd>ـٰ</i>قَ وَيَعْقُوبَ وَجَعَلْنَا فِى ذُرِّيَّتِهِ <i class=tj-silent>ٱ</i><i class=tj-silent>ل</i><i class=tj-ghunnah>نّ</i>ُبُوَّةَ وَ<i class=tj-silent>ٱ</i>لْكِتَ<i class=tj-madd>ـٰ</i>بَ وَءَاتَيْنَ<i class=tj-madd>ـٰ</i>هُ أَ<i class=tj-qalqalah>جْ</i>رَهُ<i class=tj-madd>ۥ</i> فِى <i class=tj-silent>ٱ</i><i class=tj-silent>ل</i>دُّنْيَا‌ۖ وَإِ<i class=tj-ghunnah>نّ</i>َهُ<i class=tj-madd>ۥ</i> فِى <i class=tj-silent>ٱ</i>لْأَخِرَةِ لَمِنَ <i class=tj-silent>ٱ</i><i class=tj-silent>ل</i>صَّ<i class=tj-madd>ـٰ</i>لِح<i class=tj-madd>ِي</i>نَ","28":"وَلُوطًا إِذْ قَالَ لِقَوْمِه<i class=tj-madd>ِۦٓ</i> إِ<i class=tj-ghunnah>نّ</i>َكُمْ لَتَأْتُونَ <i class=tj-silent>ٱ</i>لْفَ<i class=tj-madd>ـٰ</i>حِشَةَ مَا سَبَقَك<i class=tj-ikhfa>ُم ب</i>ِهَا مِنْ أَحَ<i class=tj-ghunnah>دٍ م</i>ِّنَ <i class=tj-silent>ٱ</i>لْعَ<i class=tj-madd>ـٰ</i>لَم<i class=tj-madd>ِي</i>نَ","29":"أَئِ<i class=tj-ghunnah>نّ</i>َكُمْ لَتَأْتُونَ <i class=tj-silent>ٱ</i><i class=tj-silent>ل</i>رِّجَالَ وَتَ<i class=tj-qalqalah>قْ</i>طَعُونَ <i class=tj-silent>ٱ</i><i class=tj-silent>ل</i>سَّبِيلَ وَتَأْتُونَ فِى نَادِيكُمُ <i class=tj-silent>ٱ</i>لْمُ<i class=tj-ikhfa>نك</i>َرَ‌ۖ فَمَا كَانَ جَوَابَ قَوْمِه<i class=tj-madd>ِۦٓ</i> إِلّ<i class=tj-madd>َآ</i> أَ<i class=tj-ikhfa>ن ق</i>َالُو<i class=tj-silent>اْ</i> <i class=tj-silent>ٱ</i>ئْتِنَا بِعَذَابِ <i class=tj-silent>ٱ</i>للَّهِ إِ<i class=tj-ikhfa>ن ك</i>ُ<i class=tj-ikhfa>نت</i>َ مِنَ <i class=tj-silent>ٱ</i><i class=tj-silent>ل</i>صَّ<i class=tj-madd>ـٰ</i>دِق<i class=tj-madd>ِي</i>نَ","30":"قَالَ رَبِّ <i class=tj-silent>ٱ</i><i class=tj-ikhfa>نص</i>ُرْنِى عَلَى <i class=tj-silent>ٱ</i>لْقَوْمِ <i class=tj-silent>ٱ</i>لْمُفْسِد<i class=tj-madd>ِي</i>نَ","31":"وَلَ<i class=tj-ghunnah>مّ</i>َا ج<i class=tj-madd>َا</i>ٓءَتْ رُسُلُن<i class=tj-madd>َآ</i> إِ<i class=tj-qalqalah>بْ</i>ر<i class=tj-madd>َٲ</i>هِيمَ بِ<i class=tj-silent>ٱ</i>لْبُشْرَىٰ قَال<i class=tj-madd>ُوٓ</i><i class=tj-silent>اْ</i> إِ<i class=tj-ghunnah>نّ</i>َا مُهْلِك<i class=tj-madd>ُوٓ</i><i class=tj-silent>اْ</i> أَهْلِ هَ<i class=tj-madd>ـٰ</i>ذِهِ <i class=tj-silent>ٱ</i>لْقَرْيَةِ‌ۖ إِ<i class=tj-ghunnah>نّ</i>َ أَهْلَهَا كَانُو<i class=tj-silent>اْ</i> ظَ<i class=tj-madd>ـٰ</i>لِم<i class=tj-madd>ِي</i>نَ","32":"قَالَ إِ<i class=tj-ghunnah>نّ</i>َ فِيهَا لُو<i class=tj-ikhfa>طًا‌ۚ ق</i>َالُو<i class=tj-silent>اْ</i> نَحْنُ أَعْلَمُ بِمَ<i class=tj-ikhfa>ن ف</i>ِيهَا‌ۖ لَنُنَجِّيَ<i class=tj-ghunnah>نّ</i>َهُ<i class=tj-madd>ۥ</i> وَأَهْلَهُ<i class=tj-madd>ۥٓ</i> إِلَّا <i class=tj-silent>ٱ</i>مْرَأَتَهُ<i class=tj-madd>ۥ</i> كَانَتْ مِنَ <i class=tj-silent>ٱ</i>لْغَ<i class=tj-madd>ـٰ</i>بِر<i class=tj-madd>ِي</i>نَ","33":"وَلَ<i class=tj-ghunnah>مّ</i><i class=tj-madd>َآ</i> أَ<i class=tj-ikhfa>ن ج</i><i class=tj-madd>َا</i>ٓءَتْ رُسُلُنَا لُو<i class=tj-ikhfa>طًا س</i><i class=tj-madd>ِى</i>ٓءَ بِهِمْ وَضَاقَ بِهِمْ ذَرْ<i class=tj-ghunnah>عًا و</i>َقَالُو<i class=tj-silent>اْ</i> لَا تَخَفْ وَلَا تَحْزَنْ‌ۖ إِ<i class=tj-ghunnah>نّ</i>َا مُنَجُّوكَ وَأَهْلَكَ إِلَّا <i class=tj-silent>ٱ</i>مْرَأَتَكَ كَانَتْ مِنَ <i class=tj-silent>ٱ</i>لْغَ<i class=tj-madd>ـٰ</i>بِر<i class=tj-madd>ِي</i>نَ","34":"إِ<i class=tj-ghunnah>نّ</i>َا مُ<i class=tj-ikhfa>نز</i>ِلُونَ عَلَ<i class=tj-madd>ىٰٓ</i> أَهْلِ هَ<i class=tj-madd>ـٰ</i>ذِهِ <i class=tj-silent>ٱ</i>لْقَرْيَةِ رِ<i class=tj-qalqalah>جْ</i><i class=tj-ghunnah>زًا م</i>ِّنَ <i class=tj-silent>ٱ</i><i class=tj-silent>ل</i>سَّم<i class=tj-madd>َا</i>ٓءِ بِمَا كَانُو<i class=tj-silent>اْ</i> يَفْسُق<i class=tj-madd>ُو</i>نَ","35":"وَلَقَ<i class=tj-silent>د</i> تَّرَكْنَا مِنْه<i class=tj-madd>َآ</i> ءَايَ<i class=tj-ikhfa>ةَۢ ب</i>َيِّنَ<i class=tj-silent>ةً ل</i>ِّقَوْ<i class=tj-ghunnah>مٍ ي</i>َعْقِل<i class=tj-madd>ُو</i>نَ","36":"وَإِلَىٰ مَ<i class=tj-qalqalah>دْ</i>يَنَ أَخَاهُمْ شُعَيْ<i class=tj-ikhfa>بًا ف</i>َقَالَ يَ<i class=tj-madd>ـٰ</i>قَوْمِ <i class=tj-silent>ٱ</i>عْبُدُو<i class=tj-silent>اْ</i> <i class=tj-silent>ٱ</i>للَّهَ وَ<i class=tj-silent>ٱ</i>رْجُو<i class=tj-silent>اْ</i> <i class=tj-silent>ٱ</i>لْيَوْمَ <i class=tj-silent>ٱ</i>لْأَخِرَ وَلَا تَعْثَوْ<i class=tj-silent>اْ</i> فِى <i class=tj-silent>ٱ</i>لْأَرْضِ مُفْسِد<i class=tj-madd>ِي</i>نَ","37":"فَكَذَّبُوهُ فَأَخَذَتْهُمُ <i class=tj-silent>ٱ</i><i class=tj-silent>ل</i>رَّ<i class=tj-qalqalah>جْ</i>فَةُ فَأَصْبَحُو<i class=tj-silent>اْ</i> فِى دَارِهِمْ جَ<i class=tj-madd>ـٰ</i>ثِم<i class=tj-madd>ِي</i>نَ","38":"وَعَا<i class=tj-ghunnah>دًا و</i>َثَمُودَ<i class=tj-silent>اْ</i> وَقَ<i class=tj-silent>د</i> تَّبَيَّنَ لَك<i class=tj-ghunnah>ُم م</i>ّ<i class=tj-ghunnah>ِن م</i>َّسَ<i class=tj-madd>ـٰ</i>كِنِهِمْ‌ۖ وَزَيَّنَ لَهُمُ <i class=tj-silent>ٱ</i><i class=tj-silent>ل</i>شَّيْطَ<i class=tj-madd>ـٰ</i>نُ أَعْمَ<i class=tj-madd>ـٰ</i>لَهُمْ فَصَدَّهُمْ عَنِ <i class=tj-silent>ٱ</i><i class=tj-silent>ل</i>سَّبِيلِ وَكَانُو<i class=tj-silent>اْ</i> مُسْتَ<i class=tj-qalqalah>بْ</i>صِر<i class=tj-madd>ِي</i>نَ","39":"وَقَ<i class=tj-madd>ـٰ</i>رُونَ وَفِرْعَوْنَ وَهَ<i class=tj-madd>ـٰ</i>مَ<i class=tj-madd>ـٰ</i>نَ‌ۖ وَلَقَ<i class=tj-qalqalah>دْ</i> ج<i class=tj-madd>َا</i>ٓءَه<i class=tj-ghunnah>ُم م</i>ُّوسَىٰ بِ<i class=tj-silent>ٱ</i>لْبَيِّنَ<i class=tj-madd>ـٰ</i>تِ فَ<i class=tj-silent>ٱ</i>سْتَكْبَرُو<i class=tj-silent>اْ</i> فِى <i class=tj-silent>ٱ</i>لْأَرْضِ وَمَا كَانُو<i class=tj-silent>اْ</i> سَ<i class=tj-madd>ـٰ</i>بِق<i class=tj-madd>ِي</i>نَ","40":"فَكُلاًّ أَخَذْنَا بِذَ<i class=tj-ikhfa>نۢب</i>ِه<i class=tj-madd>ِۦ</i>‌ۖ فَمِنْه<i class=tj-ghunnah>ُم م</i>َّنْ أَرْسَلْنَا عَلَيْهِ حَاصِ<i class=tj-ghunnah>بًا و</i>َمِنْه<i class=tj-ghunnah>ُم م</i>َّنْ أَخَذَتْهُ <i class=tj-silent>ٱ</i><i class=tj-silent>ل</i>صَّيْحَةُ وَمِنْه<i class=tj-ghunnah>ُم م</i>َّنْ خَسَفْنَا بِهِ <i class=tj-silent>ٱ</i>لْأَرْضَ وَمِنْه<i class=tj-ghunnah>ُم م</i>َّنْ أَغْرَ<i class=tj-qalqalah>قْ</i>نَا‌ۚ وَمَا كَانَ <i class=tj-silent>ٱ</i>للَّهُ لِيَظْلِمَهُمْ وَلَ<i class=tj-madd>ـٰ</i>كِ<i class=tj-ikhfa>ن ك</i>َان<i class=tj-madd>ُوٓ</i><i class=tj-silent>اْ</i> أَ<i class=tj-ikhfa>نف</i>ُسَهُمْ يَظْلِم<i class=tj-madd>ُو</i>نَ","41":"مَثَلُ <i class=tj-silent>ٱ</i>لَّذِينَ <i class=tj-silent>ٱ</i>تَّخَذُو<i class=tj-silent>اْ</i> مِ<i class=tj-ikhfa>ن د</i>ُونِ <i class=tj-silent>ٱ</i>للَّهِ أَوْلِي<i class=tj-madd>َا</i>ٓءَ كَمَثَلِ <i class=tj-silent>ٱ</i>لْعَ<i class=tj-ikhfa>نك</i>َبُوتِ <i class=tj-silent>ٱ</i>تَّخَذَتْ بَيْ<i class=tj-ghunnah>تًا‌ۖ و</i>َإِ<i class=tj-ghunnah>نّ</i>َ أَوْهَنَ <i class=tj-silent>ٱ</i>لْبُيُوتِ لَبَيْتُ <i class=tj-silent>ٱ</i>لْعَ<i class=tj-ikhfa>نك</i>َبُوتِ‌ۖ لَوْ كَانُو<i class=tj-silent>اْ</i> يَعْلَم<i class=tj-madd>ُو</i>نَ","42":"إِ<i class=tj-ghunnah>نّ</i>َ <i class=tj-silent>ٱ</i>للَّهَ يَعْلَمُ مَا يَ<i class=tj-qalqalah>دْ</i>عُونَ مِ<i class=tj-ikhfa>ن د</i>ُونِه<i class=tj-madd>ِۦ</i> مِ<i class=tj-ikhfa>ن ش</i><i class=tj-ghunnah>َىْءٍ‌ۚ و</i>َهُوَ <i class=tj-silent>ٱ</i>لْعَزِيزُ <i class=tj-silent>ٱ</i>لْحَك<i class=tj-madd>ِي</i>مُ","43":"وَتِلْكَ <i class=tj-silent>ٱ</i>لْأَمْثَ<i class=tj-madd>ـٰ</i>لُ نَضْرِبُهَا لِل<i class=tj-ghunnah>نّ</i>َاسِ‌ۖ وَمَا يَعْقِلُه<i class=tj-madd>َآ</i> إِلَّا <i class=tj-silent>ٱ</i>لْعَ<i class=tj-madd>ـٰ</i>لِم<i class=tj-madd>ُو</i>نَ","44":"خَلَقَ <i class=tj-silent>ٱ</i>للَّهُ <i class=tj-silent>ٱ</i><i class=tj-silent>ل</i>سَّمَ<i class=tj-madd>ـٰ</i>و<i class=tj-madd>َٲ</i>تِ وَ<i class=tj-silent>ٱ</i>لْأَرْضَ بِ<i class=tj-silent>ٱ</i>لْحَقِّ‌ۚ إِ<i class=tj-ghunnah>نّ</i>َ فِى ذ<i class=tj-madd>َٲ</i>لِكَ لَأَيَ<i class=tj-silent>ةً ل</i>ِّلْمُؤْمِن<i class=tj-madd>ِي</i>نَ","45":"ٱتْلُ م<i class=tj-madd>َآ</i> أُوحِىَ إِلَيْكَ مِنَ <i class=tj-silent>ٱ</i>لْكِتَ<i class=tj-madd>ـٰ</i>بِ وَأَقِمِ <i class=tj-silent>ٱ</i><i class=tj-silent>ل</i>صَّلَ<i class=tj-silent>و</i><i class=tj-madd>ٲ</i>ةَ‌ۖ إِ<i class=tj-ghunnah>نّ</i>َ <i class=tj-silent>ٱ</i><i class=tj-silent>ل</i>صَّلَ<i class=tj-silent>و</i><i class=tj-madd>ٲ</i>ةَ تَنْهَىٰ عَنِ <i class=tj-silent>ٱ</i>لْفَحْش<i class=tj-madd>َا</i>ٓءِ وَ<i class=tj-silent>ٱ</i>لْمُ<i class=tj-ikhfa>نك</i>َرِ‌ۗ وَلَذِكْرُ <i class=tj-silent>ٱ</i>للَّهِ أَكْبَرُ‌ۗ وَ<i class=tj-silent>ٱ</i>للَّهُ يَعْلَمُ مَا تَصْنَع<i class=tj-madd>ُو</i>نَ","46":"۞ وَلَا تُجَ<i class=tj-madd>ـٰ</i>دِل<i class=tj-madd>ُوٓ</i><i class=tj-silent>اْ</i> أَهْلَ <i class=tj-silent>ٱ</i>لْكِتَ<i class=tj-madd>ـٰ</i>بِ إِلَّا بِ<i class=tj-silent>ٱ</i>لَّتِى هِىَ أَحْسَنُ إِلَّا <i class=tj-silent>ٱ</i>لَّذِينَ ظَلَمُو<i class=tj-silent>اْ</i> مِنْهُمْ‌ۖ وَقُول<i class=tj-madd>ُوٓ</i><i class=tj-silent>اْ</i> ءَامَ<i class=tj-ghunnah>نّ</i>َا بِ<i class=tj-silent>ٱ</i>لَّذ<i class=tj-madd>ِىٓ</i> أُ<i class=tj-ikhfa>نز</i>ِلَ إِلَيْنَا وَأُ<i class=tj-ikhfa>نز</i>ِلَ إِلَيْكُمْ وَإِلَ<i class=tj-madd>ـٰ</i>هُنَا وَإِلَ<i class=tj-madd>ـٰ</i>هُكُمْ و<i class=tj-madd>َٲ</i>حِ<i class=tj-ghunnah>دٌ و</i>َنَحْنُ لَهُ<i class=tj-madd>ۥ</i> مُسْلِم<i class=tj-madd>ُو</i>نَ","47":"وَكَذ<i class=tj-madd>َٲ</i>لِكَ أَ<i class=tj-ikhfa>نز</i>َلْن<i class=tj-madd>َآ</i> إِلَيْكَ <i class=tj-silent>ٱ</i>لْكِتَ<i class=tj-madd>ـٰ</i>بَ‌ۚ فَ<i class=tj-silent>ٱ</i>لَّذِينَ ءَاتَيْنَ<i class=tj-madd>ـٰ</i>هُمُ <i class=tj-silent>ٱ</i>لْكِتَ<i class=tj-madd>ـٰ</i>بَ يُؤْمِنُونَ بِه<i class=tj-madd>ِۦ</i>‌ۖ وَمِنْ هَ<i class=tj-madd>ـٰٓ</i>ؤُل<i class=tj-madd>َا</i>ٓءِ م<i class=tj-ghunnah>َن ي</i>ُؤْمِنُ بِه<i class=tj-madd>ِۦ</i>‌ۚ وَمَا يَ<i class=tj-qalqalah>جْ</i>حَدُ بِـَٔـايَ<i class=tj-madd>ـٰ</i>تِن<i class=tj-madd>َآ</i> إِلَّا <i class=tj-silent>ٱ</i>لْكَ<i class=tj-madd>ـٰ</i>فِر<i class=tj-madd>ُو</i>نَ","48":"وَمَا كُ<i class=tj-ikhfa>نت</i>َ تَتْلُو<i class=tj-silent>اْ</i> مِ<i class=tj-ikhfa>ن ق</i>َ<i class=tj-qalqalah>بْ</i>لِه<i class=tj-madd>ِۦ</i> مِ<i class=tj-ikhfa>ن ك</i>ِتَ<i class=tj-madd>ـٰ</i><i class=tj-ghunnah>بٍ و</i>َلَا تَخُطُّهُ<i class=tj-madd>ۥ</i> بِيَمِينِكَ‌ۖ إِ<i class=tj-silent>ذًا ل</i>َّ<i class=tj-silent>ٱ</i>رْتَابَ <i class=tj-silent>ٱ</i>لْمُ<i class=tj-qalqalah>بْ</i>طِل<i class=tj-madd>ُو</i>نَ","49":"بَلْ هُوَ ءَايَ<i class=tj-madd>ـٰ</i><i class=tj-ikhfa>تُۢ ب</i>َيِّنَ<i class=tj-madd>ـٰ</i><i class=tj-ikhfa>تٌ ف</i>ِى صُدُورِ <i class=tj-silent>ٱ</i>لَّذِينَ أُوتُو<i class=tj-silent>اْ</i> <i class=tj-silent>ٱ</i>لْعِلْمَ‌ۚ وَمَا يَ<i class=tj-qalqalah>جْ</i>حَدُ بِـَٔـايَ<i class=tj-madd>ـٰ</i>تِن<i class=tj-madd>َآ</i> إِلَّا <i class=tj-silent>ٱ</i><i class=tj-silent>ل</i>ظَّ<i class=tj-madd>ـٰ</i>لِم<i class=tj-madd>ُو</i>نَ","50":"وَقَالُو<i class=tj-silent>اْ</i> لَوْل<i class=tj-madd>َآ</i> أُ<i class=tj-ikhfa>نز</i>ِلَ عَلَيْهِ ءَايَ<i class=tj-madd>ـٰ</i><i class=tj-ghunnah>تٌ م</i>ّ<i class=tj-silent>ِن ر</i>َّبِّه<i class=tj-madd>ِۦ</i>‌ۖ قُلْ إِ<i class=tj-ghunnah>نّ</i>َمَا <i class=tj-silent>ٱ</i>لْأَيَ<i class=tj-madd>ـٰ</i>تُ عِ<i class=tj-ikhfa>ند</i>َ <i class=tj-silent>ٱ</i>للَّهِ وَإِ<i class=tj-ghunnah>نّ</i>َم<i class=tj-madd>َآ</i> أَنَا۟ نَذِي<i class=tj-ghunnah>رٌ م</i>ُّب<i class=tj-madd>ِي</i>نٌ","51":"أَوَلَمْ يَكْفِهِمْ أَ<i class=tj-ghunnah>نّ</i><i class=tj-madd>َآ</i> أَ<i class=tj-ikhfa>نز</i>َلْنَا عَلَيْكَ <i class=tj-silent>ٱ</i>لْكِتَ<i class=tj-madd>ـٰ</i>بَ يُتْلَىٰ عَلَيْهِمْ‌ۚ إِ<i class=tj-ghunnah>نّ</i>َ فِى ذ<i class=tj-madd>َٲ</i>لِكَ لَرَحْمَ<i class=tj-ghunnah>ةً و</i>َذِكْرَىٰ لِقَوْ<i class=tj-ghunnah>مٍ ي</i>ُؤْمِن<i class=tj-madd>ُو</i>نَ","52":"قُلْ كَفَىٰ بِ<i class=tj-silent>ٱ</i>للَّهِ بَيْنِى وَبَيْنَكُمْ شَهِي<i class=tj-ghunnah>دًا‌ۖ ي</i>َعْلَمُ مَا فِى <i class=tj-silent>ٱ</i><i class=tj-silent>ل</i>سَّمَ<i class=tj-madd>ـٰ</i>و<i class=tj-madd>َٲ</i>تِ وَ<i class=tj-silent>ٱ</i>لْأَرْضِ‌ۗ وَ<i class=tj-silent>ٱ</i>لَّذِينَ ءَامَنُو<i class=tj-silent>اْ</i> بِ<i class=tj-silent>ٱ</i>لْبَ<i class=tj-madd>ـٰ</i>طِلِ وَكَفَرُو<i class=tj-silent>اْ</i> بِ<i class=tj-silent>ٱ</i>للَّهِ أُ<i class=tj-silent>وْ</i>لَ<i class=tj-madd>ـٰٓ</i>ئِكَ هُمُ <i class=tj-silent>ٱ</i>لْخَ<i class=tj-madd>ـٰ</i>سِر<i class=tj-madd>ُو</i>نَ","53":"وَيَسْتَعْجِلُونَكَ بِ<i class=tj-silent>ٱ</i>لْعَذَابِ‌ۚ وَلَوْل<i class=tj-madd>َآ</i> أَجَ<i class=tj-ghunnah>لٌ م</i>ُّسَم<i class=tj-silent>ًّى ل</i>َّج<i class=tj-madd>َا</i>ٓءَهُمُ <i class=tj-silent>ٱ</i>لْعَذَابُ وَلَيَأْتِيَ<i class=tj-ghunnah>نّ</i>َه<i class=tj-ikhfa>ُم ب</i>َغْتَ<i class=tj-ghunnah>ةً و</i>َهُمْ لَا يَشْعُر<i class=tj-madd>ُو</i>نَ","54":"يَسْتَعْجِلُونَكَ بِ<i class=tj-silent>ٱ</i>لْعَذَابِ وَإِ<i class=tj-ghunnah>نّ</i>َ جَهَ<i class=tj-ghunnah>نّ</i>َمَ لَمُحِيطَ<i class=tj-ikhfa>ةُۢ ب</i>ِ<i class=tj-silent>ٱ</i>لْكَ<i class=tj-madd>ـٰ</i>فِر<i class=tj-madd>ِي</i>نَ","55":"يَوْمَ يَغْشَ<i class=tj-madd>ـٰ</i>هُمُ <i class=tj-silent>ٱ</i>لْعَذَابُ مِ<i class=tj-ikhfa>ن ف</i>َوْقِهِمْ وَمِ<i class=tj-ikhfa>ن ت</i>َحْتِ أَرْجُلِهِمْ وَيَقُولُ ذُوقُو<i class=tj-silent>اْ</i> مَا كُ<i class=tj-ikhfa>نت</i>ُمْ تَعْمَل<i class=tj-madd>ُو</i>نَ","56":"يَ<i class=tj-madd>ـٰ</i>عِبَادِىَ <i class=tj-silent>ٱ</i>لَّذِينَ ءَامَن<i class=tj-madd>ُوٓ</i><i class=tj-silent>اْ</i> إِ<i class=tj-ghunnah>نّ</i>َ أَرْضِى و<i class=tj-madd>َٲ</i>سِعَ<i class=tj-ikhfa>ةٌ ف</i>َإِيَّ<i class=tj-madd>ـٰ</i>ىَ فَ<i class=tj-silent>ٱ</i>عْبُد<i class=tj-madd>ُو</i>نِ","57":"كُلُّ نَفْ<i class=tj-ikhfa>سٍ ذ</i><i class=tj-madd>َا</i>ٓئِقَةُ <i class=tj-silent>ٱ</i>لْمَوْتِ‌ۖ ثُ<i class=tj-ghunnah>مّ</i>َ إِلَيْنَا تُرْجَع<i class=tj-madd>ُو</i>نَ","58":"وَ<i class=tj-silent>ٱ</i>لَّذِينَ ءَامَنُو<i class=tj-silent>اْ</i> وَعَمِلُو<i class=tj-silent>اْ</i> <i class=tj-silent>ٱ</i><i class=tj-silent>ل</i>صَّ<i class=tj-madd>ـٰ</i>لِحَ<i class=tj-madd>ـٰ</i>تِ لَنُبَوِّئَ<i class=tj-ghunnah>نّ</i>َه<i class=tj-ghunnah>ُم م</i>ِّنَ <i class=tj-silent>ٱ</i>لْجَ<i class=tj-ghunnah>نّ</i>َةِ غُرَ<i class=tj-ikhfa>فًا ت</i>َ<i class=tj-qalqalah>جْ</i>رِى مِ<i class=tj-ikhfa>ن ت</i>َحْتِهَا <i class=tj-silent>ٱ</i>لْأَنْهَ<i class=tj-madd>ـٰ</i>رُ خَ<i class=tj-madd>ـٰ</i>لِدِينَ فِيهَا‌ۚ نِعْمَ أَ<i class=tj-qalqalah>جْ</i>رُ <i class=tj-silent>ٱ</i>لْعَ<i class=tj-madd>ـٰ</i>مِل<i class=tj-madd>ِي</i>نَ","59":"ٱلَّذِينَ صَبَرُو<i class=tj-silent>اْ</i> وَعَلَىٰ رَبِّهِمْ يَتَوَكَّل<i class=tj-madd>ُو</i>نَ","60":"وَكَأَيّ<i class=tj-ghunnah>ِن م</i>ِّ<i class=tj-ikhfa>ن د</i><i class=tj-madd>َا</i>ٓبَّ<i class=tj-silent>ةٍ ل</i>َّا تَحْمِلُ رِزْقَهَا <i class=tj-silent>ٱ</i>للَّهُ يَرْزُقُهَا وَإِيَّاكُمْ‌ۚ وَهُوَ <i class=tj-silent>ٱ</i><i class=tj-silent>ل</i>سَّمِيعُ <i class=tj-silent>ٱ</i>لْعَل<i class=tj-madd>ِي</i>مُ","61":"وَلَئِ<i class=tj-ikhfa>ن س</i>َأَلْتَه<i class=tj-ghunnah>ُم م</i>َّنْ خَلَقَ <i class=tj-silent>ٱ</i><i class=tj-silent>ل</i>سَّمَ<i class=tj-madd>ـٰ</i>و<i class=tj-madd>َٲ</i>تِ وَ<i class=tj-silent>ٱ</i>لْأَرْضَ وَسَخَّرَ <i class=tj-silent>ٱ</i><i class=tj-silent>ل</i>شَّمْسَ وَ<i class=tj-silent>ٱ</i>لْقَمَرَ لَيَقُولُ<i class=tj-ghunnah>نّ</i>َ <i class=tj-silent>ٱ</i>للَّهُ‌ۖ فَأَ<i class=tj-ghunnah>نّ</i>َىٰ يُؤْفَك<i class=tj-madd>ُو</i>نَ","62":"ٱللَّهُ يَ<i class=tj-qalqalah>بْ</i>سُطُ <i class=tj-silent>ٱ</i><i class=tj-silent>ل</i>رِّزْقَ لِم<i class=tj-ghunnah>َن ي</i>َش<i class=tj-madd>َا</i>ٓءُ مِنْ عِبَادِه<i class=tj-madd>ِۦ</i> وَيَ<i class=tj-qalqalah>قْ</i>دِرُ لَهُ<i class=tj-madd>ۥٓ‌ۚ</i> إِ<i class=tj-ghunnah>نّ</i>َ <i class=tj-silent>ٱ</i>للَّهَ بِكُلِّ شَىْءٍ عَل<i class=tj-madd>ِي</i>مٌ","63":"وَلَئِ<i class=tj-ikhfa>ن س</i>َأَلْتَه<i class=tj-ghunnah>ُم م</i>ّ<i class=tj-ghunnah>َن ن</i>َّزَّلَ مِنَ <i class=tj-silent>ٱ</i><i class=tj-silent>ل</i>سَّم<i class=tj-madd>َا</i>ٓءِ م<i class=tj-madd>َا</i>ٓ<i class=tj-ikhfa>ءً ف</i>َأَحْيَا بِهِ <i class=tj-silent>ٱ</i>لْأَرْضَ م<i class=tj-ikhfa>ِنۢ ب</i>َعْدِ مَوْتِهَا لَيَقُولُ<i class=tj-ghunnah>نّ</i>َ <i class=tj-silent>ٱ</i>للَّهُ‌ۚ قُلِ <i class=tj-silent>ٱ</i>لْحَمْدُ لِلَّهِ‌ۚ بَلْ أَكْثَرُهُمْ لَا يَعْقِل<i class=tj-madd>ُو</i>نَ","64":"وَمَا هَ<i class=tj-madd>ـٰ</i>ذِهِ <i class=tj-silent>ٱ</i>لْحَيَ<i class=tj-silent>و</i><i class=tj-madd>ٲ</i>ةُ <i class=tj-silent>ٱ</i><i class=tj-silent>ل</i>دُّنْي<i class=tj-madd>َآ</i> إِلَّا لَهْ<i class=tj-ghunnah>وٌ و</i>َلَعِ<i class=tj-ghunnah>بٌ‌ۚ و</i>َإِ<i class=tj-ghunnah>نّ</i>َ <i class=tj-silent>ٱ</i><i class=tj-silent>ل</i>دَّارَ <i class=tj-silent>ٱ</i>لْأَخِرَةَ لَهِىَ <i class=tj-silent>ٱ</i>لْحَيَوَانُ‌ۚ لَوْ كَانُو<i class=tj-silent>اْ</i> يَعْلَم<i class=tj-madd>ُو</i>نَ","65":"فَإِذَا رَكِبُو<i class=tj-silent>اْ</i> فِى <i class=tj-silent>ٱ</i>لْفُلْكِ دَعَوُ<i class=tj-silent>اْ</i> <i class=tj-silent>ٱ</i>للَّهَ مُخْلِصِينَ لَهُ <i class=tj-silent>ٱ</i><i class=tj-silent>ل</i>دِّينَ فَلَ<i class=tj-ghunnah>مّ</i>َا نَجَّ<i class=tj-madd>ـٰ</i>هُمْ إِلَى <i class=tj-silent>ٱ</i>لْبَرِّ إِذَا هُمْ يُشْرِك<i class=tj-madd>ُو</i>نَ","66":"لِيَكْفُرُو<i class=tj-silent>اْ</i> بِم<i class=tj-madd>َآ</i> ءَاتَيْنَ<i class=tj-madd>ـٰ</i>هُمْ وَلِيَتَمَتَّعُو<i class=tj-silent>اْ‌ۖ</i> فَسَوْفَ يَعْلَم<i class=tj-madd>ُو</i>نَ","67":"أَوَلَمْ يَرَوْ<i class=tj-silent>اْ</i> أَ<i class=tj-ghunnah>نّ</i>َا جَعَلْنَا حَرَمًا ءَامِ<i class=tj-ghunnah>نًا و</i>َيُتَخَطَّفُ <i class=tj-silent>ٱ</i><i class=tj-silent>ل</i><i class=tj-ghunnah>نّ</i>َاسُ مِنْ حَوْلِهِمْ‌ۚ أَفَبِ<i class=tj-silent>ٱ</i>لْبَ<i class=tj-madd>ـٰ</i>طِلِ يُؤْمِنُونَ وَبِنِعْمَةِ <i class=tj-silent>ٱ</i>للَّهِ يَكْفُر<i class=tj-madd>ُو</i>نَ","68":"وَمَنْ أَظْلَمُ مِ<i class=tj-ghunnah>مّ</i>َنِ <i class=tj-silent>ٱ</i>فْتَرَىٰ عَلَى <i class=tj-silent>ٱ</i>للَّهِ كَذِبًا أَوْ كَذَّبَ بِ<i class=tj-silent>ٱ</i>لْحَقِّ لَ<i class=tj-ghunnah>مّ</i>َا ج<i class=tj-madd>َا</i>ٓءَهُ<i class=tj-madd>ۥٓ‌ۚ</i> أَلَيْسَ فِى جَهَ<i class=tj-ghunnah>نّ</i>َمَ مَثْ<i class=tj-silent>وًى ل</i>ِّلْكَ<i class=tj-madd>ـٰ</i>فِر<i class=tj-madd>ِي</i>نَ","69":"وَ<i class=tj-silent>ٱ</i>لَّذِينَ جَ<i class=tj-madd>ـٰ</i>هَدُو<i class=tj-silent>اْ</i> فِينَا لَنَهْدِيَ<i class=tj-ghunnah>نّ</i>َهُمْ سُبُلَنَا‌ۚ وَإِ<i class=tj-ghunnah>نّ</i>َ <i class=tj-silent>ٱ</i>للَّهَ لَمَعَ <i class=tj-silent>ٱ</i>لْمُحْسِن<i class=tj-madd>ِي</i>نَ"}}